Workbook

Sheet README
A1: PRELIMINARY — SCREENING ONLY, NON-DECISION-GRADE (revised per technical review)
A2: Base case now excludes LCFS, IRA 45V, CCS and $/kg offtake revenue (all behind explicit toggles in Global_Assumptions); H2 energy basis is LHV-consistent; NPV is reported incremental to the 0% baseline. See the Corrections_Log and Validation_Tests sheets. Do NOT use LCOH/NPV/abatement figures for investment decisions or cross-site ranking.
A5: HARMONIZED H2 TEA + RELIABILITY MODEL — UCI Microturbine
A6: UCI Capstone C200 Microturbine (~200 kW)
A8: Harmonization note | B8: This workbook is one of five case studies built on a single harmonized template. The Global_Assumptions sheet, all formulas, the PoF thresholds (FCGR multipliers, base leak/burst rates, 20-yr horizon) and the inspection/maintenance unit costs are IDENTICAL across every case study. Only the Component_Register and system parameters differ by configuration.
A10: System type | B10: End-use delivery (low demand)
A11: End use | B11: Capstone C200 microturbine (~200 kW)
A12: Operating / native pressure | B12: 44 psig (~3 bar)
A13: Pipe / lateral | B13: API 5L B, 2-in OD, 0.154-in WT, MOP 200 psi, 1 mi, 1 segment(s)
A15: SHEET INDEX
A16: 1. README | B16: This sheet
A17: 2. Global_Assumptions | B17: Shared inputs — IDENTICAL across all case studies (blue = master inputs)
A18: 3. Component_Register | B18: System-specific components and counts
A19: 4. Reliability_Inputs | B19: OREDA failure-mode rates (LB/mean/UB) per component
A20: 5. H2_Effect | B20: Hydrogen amplification by pressure band + FCGR multipliers (thresholds)
A21: 6. Failure_Rates | B21: PoF(20yr)=1-EXP(-rate*8760*horizon) — base & H2
A22: 7. Pipe_Integrity | B22: Fracture-mechanics pipe PoF vs blend (FCGR thresholds)
A23: 8. PoF_Summary | B23: Component-level PoF20 with amber/red flags (harmonized thresholds)
A24: 9. Inspection_Maint | B24: I&M plan; common-pipe unit costs from Global_Assumptions
A25: 10. Blend_Properties | B25: Volume→energy fraction, flow factor, H2 demand (kg/yr) by blend
A26: 11. TEA_CAPEX | B26: Retrofit/new pipeline, injection/compression, storage, CCS/NCD
A27: 12. TEA_Hydraulics | B27: Pressure drop & compressor count, near vs 100-mi injection
... A37: 22. Use_Case_Summary | B37: Compiled cost breakdown, drivers, feasibility thresholds
A39: Colour key
A40: Blue = hardcoded input | B40: Black = formula/derived
A41: Green = cross-sheet reference

Sheet Global_Assumptions
A1: GLOBAL ASSUMPTIONS — shared across all harmonized case studies
A2: IDENTICAL in every workbook. Blue = master input. Change here to propagate everywhere.
A3: Parameter | B3: Value | C3: Unit | D3: Source / note
A4: A. ECONOMIC BASIS
A5: Capital cost recovery factor (CCRF) | B5: 0.14 | C5: fraction | D5: [P1][P2] DOE H2A
A6: CCRF (on-site electrolysis) | B6: 0.15 | C6: fraction | D6: [P2]
A7: Utility discount rate | B7: 0.08 | C7: fraction | D7: [P3]
A8: Hurdle rate (blended) | B8: 0.0575 | C8: fraction | D8: [P3]
A9: Inflation de-escalator | B9: 0.025 | C9: fraction | D9: [P2]
A10: Project economic life / lifecycle horizon | B10: 50 | C10: years | D10: 50-yr lifecycle
A11: System availability (derived prior; see Lifecycle_50yr) | B11: =Lifecycle_50yr!$B$15 | C11: fraction | D11: Derived 50-yr mean from Lifecycle_50yr (single availability series). [corrected]
A12: B. PRICES & CARBON VALUE
A13: RH2 commodity cost (base) | B13: 2 | C13: $/kg | D13: [P1][P2]
A14: RH2 commodity (low) | B14: 1.5 | C14: $/kg | D14: [P1]
A15: RH2 commodity (high) | B15: 3 | C15: $/kg | D15: [P1]
A16: Natural gas price 2025 | B16: 4.74 | C16: $/GJ (UCI $5/MMBtu) | D16: [P3]
A17: Natural gas price 2050 | B17: 4.39 | C17: $/GJ | D17: [P3]
A18: Grid renewable electricity | B18: 235 | C18: $/MWh (UCI blended $0.235/kWh) | D18: [P2]
A19: Electricity unit cost | B19: =Global_Assumptions!$B$18/1000 | C19: $/kWh | D19: from elec_mwh/1000
A20: LCFS carbon credit | B20: =IF($B$83=1,$B$84,0) | C20: $/credit | D20: Gated: 0 unless LCFS eligible=1 (then LCFS price). [corrected]
A21: IRA 45V PTC (levelized reduction) | B21: =IF($B$85=1,-1.35,0) | C21: $/kg | D21: Gated: 0 unless 45V eligible=1. [corrected]
A22: C. PHYSICAL CONSTANTS
A23: H2 higher heating value | B23: 39.4 | C23: kWh/kg | D23: physical
A24: H2 lower heating value | B24: 33.3 | C24: kWh/kg | D24: physical
A25: H2 energy content | B25: =B24*0.0036 | C25: GJ/kg | D25: LHV-consistent: LHV_kWh*0.0036 GJ/kg (was 0.113745, ~5.4% low). [corrected]
A26: H2/NG volumetric energy ratio (k) | B26: 0.336 | C26: - | D26: physical
A27: CO2 displaced per kg zero-C H2 | B27: 7.13 | C27: kgCO2/kg | D27: derived
A28: H2 GWP100 (leakage CO2e) | B28: 11.6 | C28: - | D28: [R7] Sand 2023
A29: H2 leakage fraction (base) | B29: 0.005 | C29: fraction | D29: [R7][U2]
A30: D. CCS & NOx CAPTURE/DESTRUCTION
A31: CO2 capture fraction | B31: =IF($B$82=1,0.9,0) | C31: fraction | D31: Gated: capture only when CCS enabled=1 -> no scenario charged CCS in base. [corrected]
A32: CCS unit cost - industrial | B32: 60 | C32: $/tCO2 | D32: [P3] Tbl 3
A33: CCS unit cost - power gen | B33: 90 | C33: $/tCO2 | D33: [P3] Tbl 3
A34: CCS unit cost - DAC | B34: 225 | C34: $/tCO2 | D34: [P3] Tbl 3
A35: NCD (SCR) base cost @0% blend | B35: 8 | C35: $/tCO2e | D35: [U2] placeholder
A36: NCD additional per unit blend | B36: 6 | C36: $/tCO2e | D36: [U2] placeholder
A37: E. COMPRESSION & HYDRAULICS
A38: Compression energy | B38: 3.1 | C38: kWh/kg | D38: [R4] DOE avg
A39: Compressor CAPEX | B39: 0.75 | C39: $M/MW | D39: MDPI 2026
A40: Compressor efficiency | B40: 0.75 | C40: fraction | D40: [R4]
A41: Compressor maintenance | B41: 0.03 | C41: frac CAPEX/yr | D41: [R4] DOE
A42: Compressor station spacing | B42: 60 | C42: miles | D42: [R3] HyBlend
A43: F. CAPEX UNIT COSTS
A44: New purpose-built pipeline | B44: 4 | C44: $M/mile | D44: [P3]
A45: Retrofit/repurpose factor | B45: 0.2 | C45: fraction | D45: [P3][R5] EHB
A46: New H2 pipe premium vs NG | B46: 1.3 | C46: multiplier | D46: [R5]
A47: Injection+metering+control skid | B47: 2 | C47: $M/point | D47: [P2]
A48: On-site storage CAPEX | B48: 265 | C48: $/kg | D48: [P2] Reed 2024
A49: Storage buffer duration | B49: 1 | C49: days | D49: [U2]
A50: Pipeline O&M | B50: 0.012 | C50: frac CAPEX/yr | D50: [R5] EHB
A51: G. RELIABILITY / PoF THRESHOLDS
A52: PoF assessment horizon | B52: 20 | C52: years | D52: harmonized
A53: Pipe base annual leak rate | B53: 1e-06 | C53: /hr | D53: screening anchor
A54: Pipe base annual burst rate | B54: 5e-08 | C54: /hr | D54: screening anchor
A55: PoF amber threshold | B55: 0.3 | C55: fraction | D55: harmonized flag
A56: PoF red threshold | B56: 0.6 | C56: fraction | D56: harmonized flag
A57: H. INSPECTION & MAINTENANCE UNIT COSTS (common pipe)
A58: Inspection - normal pipeline | B58: 52361 | C58: $/mile/yr | D58: blended ILI/HT/DA
A59: Inspection - purpose-built | B59: 26180 | C59: $/mile/yr | D59: less frequent
A60: ILI frequency | B60: 7 | C60: years | D60: PHMSA
A61: ILI cost | B61: 33450 | C61: $/mile | D61: NPV 5%
A62: I. LIFECYCLE, FUEL & CASHFLOW (50-year extension)
A63: Lifecycle / cashflow horizon | B63: 50 | C63: years | D63: 50-yr extension
A64: Combustion-efficiency gain per 100% blend (Thermoflex) | B64: 0.01 | C64: fraction (+=gain; Thermoflex) | D64: screening [R13]
A65: Storage O&M (annual % of CAPEX) | B65: 0.02 | C65: frac CAPEX/yr | D65: [P2]
A66: H2 production value (generation revenue) | B66: =IF($B$87=1,4,0) | C66: $/kg | D66: Gated: 0 unless offtake revenue enabled=1 (avoids double counting). [corrected]
A67: Delivered NG retail tariff (transport revenue) | B67: 8 | C67: $/GJ | D67: [P3] retail
A68: IRA 45V credit magnitude (revenue) | B68: =IF($B$85=1,1.35,0) | C68: $/kg | D68: Gated: 0 unless 45V eligible=1; capped at 45V duration years in cashflow. [corrected]
A70: FCGR multiplier by blend (pipe PoF threshold)
A71: Blend % | B71: FCGR mult
A72: 0 | B72: 1
A73: 5 | B73: 6
A74: 10 | B74: 8
A75: 20 | B75: 10
A76: 30 | B76: 10
A77: 50 | B77: 10
A78: 75 | B78: 10
A79: 100 | B79: 10
A81: J. SCENARIO TOGGLES & POLICY ELIGIBILITY (review corrections)
A82: CCS enabled (1=on, 0=off) | B82: 0 | C82: switch | D82: [review scenario lever]
A83: LCFS eligible (1=yes, 0=no) | B83: 0 | C83: switch | D83: [review scenario lever]
A84: LCFS price if eligible | B84: 66 | C84: $/tCO2e | D84: [review scenario lever]
A85: IRA 45V eligible (1=yes, 0=no) | B85: 0 | C85: switch | D85: [review scenario lever]
A86: IRA 45V credit duration | B86: 10 | C86: years | D86: [review scenario lever]
A87: H2 offtake/production revenue enabled (1/0) | B87: 0 | C87: switch | D87: [review scenario lever]

Sheet Component_Register
A1: COMPONENT REGISTER — UCI Microturbine
A2: System-specific components. Reliability and I&M layers act on these.
A3: Component | B3: Count | C3: Class | D3: Pressure (psig) | E3: Note
A4: Delivery Lateral Pipe | B4: 1 | C4: pipe | D4: 44 | E4: in inspection/maintenance register
A5: Injection/Isolation Valve | B5: 3 | C5: valve | D5: 44 | E5: in inspection/maintenance register
A6: Pressure Regulator | B6: 1 | C6: regulator | D6: 44 | E6: in inspection/maintenance register
A7: Meter | B7: 1 | C7: meter | D7: 44 | E7: in inspection/maintenance register
A8: Buffer Storage | B8: 1 | C8: storage | D8: 44 | E8: in inspection/maintenance register
A9: Capstone C200 Microturbine | B9: 1 | C9: microturbine | D9: 44 | E9: in inspection/maintenance register
A10: Recuperator Heat Exchanger | B10: 1 | C10: heat_exchanger | D10: 44 | E10: in inspection/maintenance register

Sheet Reliability_Inputs
A1: RELIABILITY INPUTS — OREDA failure-mode rates
A2: Blue = OREDA hardcoded rates (identical per component type across all case studies).
A3: Component | B3: Failure mode | C3: FM | D3: Rate LB (/hr) | E3: Rate mean (/hr) | F3: Rate UB (/hr) | G3: H2 mult | H3: Source
A4: Injection/Isolation Valve | B4: Abnormal instrument reading | C4: AIR | D4: 2.59e-06 | E4: 1.69e-05 | F4: 4.17e-05 | G4: =H2_Effect!H5 | H4: OREDA valve
A5: Injection/Isolation Valve | B5: External leakage | C5: EL | D5: 2.38e-07 | E5: 8.11e-06 | F5: 2.77e-05 | G5: =H2_Effect!H7 | H5: OREDA valve
A6: Injection/Isolation Valve | B6: Minor in-service problems | C6: SER | D6: 3.04e-06 | E6: 2.58e-05 | F6: 6.73e-05 | G6: =H2_Effect!H12 | H6: OREDA valve
A7: Pressure Regulator | B7: Abnormal instrument reading | C7: AIR | E7: 2.14e-07 | G7: 1 | H7: OREDA regulator
A8: Pressure Regulator | B8: Delayed operation | C8: DEL | E8: 4.03e-07 | G8: 1 | H8: OREDA regulator
A9: Pressure Regulator | B9: External leakage | C9: EL | E9: 3.68e-07 | G9: 1 | H9: OREDA regulator
A10: Pressure Regulator | B10: Internal leakage | C10: IL | E10: 9.99e-07 | G10: 1 | H10: OREDA regulator
A11: Pressure Regulator | B11: Minor in-service problems | C11: SER | E11: 7.6e-07 | G11: 1 | H11: OREDA regulator
A12: Pressure Regulator | B12: Spurious operation | C12: SPO | E12: 8.95e-08 | G12: 1 | H12: OREDA regulator
A13: Pressure Regulator | B13: Structural deficiency | C13: STR | E13: 2.34e-07 | G13: 1 | H13: OREDA regulator
A14: Pressure Regulator | B14: Pressure control failure | C14: PCT | E14: 7.31e-07 | G14: 1 | H14: OREDA regulator
A15: Meter | B15: Abnormal instrument reading | C15: AIR | E15: 2.26e-05 | G15: 1 | H15: NGRMS meter

Sheet H2_Effect
A1: HYDROGEN EFFECT — amplification by pressure band + FCGR thresholds
A2: Applied band selected by native pressure (3 bar). Amplification = applied%/No-H2%.
A3: Native pressure (bar) | B3: 3
A4: FM | B4: Failure mode | C4: No-H2 % | D4: 0-5 bar % | E4: 5-20 bar % | F4: 20-100 bar % | G4: Applied % | H4: Amplification
A5: AIR | B5: Abnormal instrument reading | C5: 4.3 | D5: 4.3 | E5: 4.3 | F5: 4.3 | G5: =IF($B$3<5,D5,IF($B$3<20,E5,F5)) | H5: =G5/C5
A6: DEL | B6: Delayed operation | C6: 12.5 | D6: 32.9 | E6: 62.5 | F6: 67.5 | G6: =IF($B$3<5,D6,IF($B$3<20,E6,F6)) | H6: =G6/C6
A7: EL | B7: External leakage | C7: 12.3 | D7: 29.6 | E7: 48.8 | F7: 57.6 | G7: =IF($B$3<5,D7,IF($B$3<20,E7,F7)) | H7: =G7/C7
A8: FTC | B8: Fail to close | C8: 15.8 | D8: 25.9 | E8: 42.5 | F8: 47.8 | G8: =IF($B$3<5,D8,IF($B$3<20,E8,F8)) | H8: =G8/C8
A9: FTO | B9: Fail to open | C9: 19.1 | D9: 34.7 | E9: 51.1 | F9: 61.2 | G9: =IF($B$3<5,D9,IF($B$3<20,E9,F9)) | H9: =G9/C9
A10: IL | B10: Internal leakage | C10: 4.4 | D10: 8.3 | E10: 19.4 | F10: 13.9 | G10: =IF($B$3<5,D10,IF($B$3<20,E10,F10)) | H10: =G10/C10
A11: VLC | B11: Valve leakage in closed pos. | C11: 13.1 | D11: 29.1 | E11: 48.1 | F11: 55.8 | G11: =IF($B$3<5,D11,IF($B$3<20,E11,F11)) | H11: =G11/C11
A12: SER | B12: Minor in-service problems | C12: 8.9 | D12: 13.7 | E12: 15 | F12: 16.9 | G12: =IF($B$3<5,D12,IF($B$3<20,E12,F12)) | H12: =G12/C12
A13: SPO | B13: Spurious operation | C13: 1.8 | D13: 1.8 | E13: 1.8 | F13: 1.8 | G13: =IF($B$3<5,D13,IF($B$3<20,E13,F13)) | H13: =G13/C13
A14: STR | B14: Structural deficiency | C14: 9.3 | D14: 26.6 | E14: 43.8 | F14: 54.5 | G14: =IF($B$3<5,D14,IF($B$3<20,E14,F14)) | H14: =G14/C14
A16: FCGR multipliers (pipe-body fatigue) — see Global_Assumptions

Sheet Failure_Rates
A1: FAILURE RATES, MTTF & 20-YEAR PoF
A2: PoF(20yr)=1-EXP(-rate*8760*horizon). Horizon and basis from Global_Assumptions.
A3: Component | B3: Failure mode | C3: FM | D3: Mean rate (/hr) | E3: H2 mult | F3: H2 rate (/hr) | G3: MTTF (yr) | H3: PoF20 base | I3: PoF20 H2
A4: =Reliability_Inputs!A4 | B4: =Reliability_Inputs!B4 | C4: =Reliability_Inputs!C4 | D4: =Reliability_Inputs!E4 | E4: =Reliability_Inputs!G4 | F4: =D4*E4 | G4: =IF(D4>0,1/(D4*8760),"-") | H4: =1-EXP(-D4*8760*Global_Assumptions!$B$52) | I4: =1-EXP(-F4*8760*Global_Assumptions!$B$52)
A5: =Reliability_Inputs!A5 | B5: =Reliability_Inputs!B5 | C5: =Reliability_Inputs!C5 | D5: =Reliability_Inputs!E5 | E5: =Reliability_Inputs!G5 | F5: =D5*E5 | G5: =IF(D5>0,1/(D5*8760),"-") | H5: =1-EXP(-D5*8760*Global_Assumptions!$B$52) | I5: =1-EXP(-F5*8760*Global_Assumptions!$B$52)
A6: =Reliability_Inputs!A6 | B6: =Reliability_Inputs!B6 | C6: =Reliability_Inputs!C6 | D6: =Reliability_Inputs!E6 | E6: =Reliability_Inputs!G6 | F6: =D6*E6 | G6: =IF(D6>0,1/(D6*8760),"-") | H6: =1-EXP(-D6*8760*Global_Assumptions!$B$52) | I6: =1-EXP(-F6*8760*Global_Assumptions!$B$52)
A7: =Reliability_Inputs!A7 | B7: =Reliability_Inputs!B7 | C7: =Reliability_Inputs!C7 | D7: =Reliability_Inputs!E7 | E7: =Reliability_Inputs!G7 | F7: =D7*E7 | G7: =IF(D7>0,1/(D7*8760),"-") | H7: =1-EXP(-D7*8760*Global_Assumptions!$B$52) | I7: =1-EXP(-F7*8760*Global_Assumptions!$B$52)
A8: =Reliability_Inputs!A8 | B8: =Reliability_Inputs!B8 | C8: =Reliability_Inputs!C8 | D8: =Reliability_Inputs!E8 | E8: =Reliability_Inputs!G8 | F8: =D8*E8 | G8: =IF(D8>0,1/(D8*8760),"-") | H8: =1-EXP(-D8*8760*Global_Assumptions!$B$52) | I8: =1-EXP(-F8*8760*Global_Assumptions!$B$52)
A9: =Reliability_Inputs!A9 | B9: =Reliability_Inputs!B9 | C9: =Reliability_Inputs!C9 | D9: =Reliability_Inputs!E9 | E9: =Reliability_Inputs!G9 | F9: =D9*E9 | G9: =IF(D9>0,1/(D9*8760),"-") | H9: =1-EXP(-D9*8760*Global_Assumptions!$B$52) | I9: =1-EXP(-F9*8760*Global_Assumptions!$B$52)
A10: =Reliability_Inputs!A10 | B10: =Reliability_Inputs!B10 | C10: =Reliability_Inputs!C10 | D10: =Reliability_Inputs!E10 | E10: =Reliability_Inputs!G10 | F10: =D10*E10 | G10: =IF(D10>0,1/(D10*8760),"-") | H10: =1-EXP(-D10*8760*Global_Assumptions!$B$52) | I10: =1-EXP(-F10*8760*Global_Assumptions!$B$52)
A11: =Reliability_Inputs!A11 | B11: =Reliability_Inputs!B11 | C11: =Reliability_Inputs!C11 | D11: =Reliability_Inputs!E11 | E11: =Reliability_Inputs!G11 | F11: =D11*E11 | G11: =IF(D11>0,1/(D11*8760),"-") | H11: =1-EXP(-D11*8760*Global_Assumptions!$B$52) | I11: =1-EXP(-F11*8760*Global_Assumptions!$B$52)
A12: =Reliability_Inputs!A12 | B12: =Reliability_Inputs!B12 | C12: =Reliability_Inputs!C12 | D12: =Reliability_Inputs!E12 | E12: =Reliability_Inputs!G12 | F12: =D12*E12 | G12: =IF(D12>0,1/(D12*8760),"-") | H12: =1-EXP(-D12*8760*Global_Assumptions!$B$52) | I12: =1-EXP(-F12*8760*Global_Assumptions!$B$52)
A13: =Reliability_Inputs!A13 | B13: =Reliability_Inputs!B13 | C13: =Reliability_Inputs!C13 | D13: =Reliability_Inputs!E13 | E13: =Reliability_Inputs!G13 | F13: =D13*E13 | G13: =IF(D13>0,1/(D13*8760),"-") | H13: =1-EXP(-D13*8760*Global_Assumptions!$B$52) | I13: =1-EXP(-F13*8760*Global_Assumptions!$B$52)
A14: =Reliability_Inputs!A14 | B14: =Reliability_Inputs!B14 | C14: =Reliability_Inputs!C14 | D14: =Reliability_Inputs!E14 | E14: =Reliability_Inputs!G14 | F14: =D14*E14 | G14: =IF(D14>0,1/(D14*8760),"-") | H14: =1-EXP(-D14*8760*Global_Assumptions!$B$52) | I14: =1-EXP(-F14*8760*Global_Assumptions!$B$52)
A15: =Reliability_Inputs!A15 | B15: =Reliability_Inputs!B15 | C15: =Reliability_Inputs!C15 | D15: =Reliability_Inputs!E15 | E15: =Reliability_Inputs!G15 | F15: =D15*E15 | G15: =IF(D15>0,1/(D15*8760),"-") | H15: =1-EXP(-D15*8760*Global_Assumptions!$B$52) | I15: =1-EXP(-F15*8760*Global_Assumptions!$B$52)

Sheet Pipe_Integrity
A1: PIPE-BODY INTEGRITY SCREENING — UCI Microturbine
A2: API 5L B: 2-in OD, 0.154-in WT. FCGR mult & base rates from Global_Assumptions (harmonized thresholds).
A3: Flaw length-to-depth ratio | B3: 15
A4: SMYS (psi) | B4: 35000
A5: KIC (MPa.m^0.5) | B5: 55
A6: OD (in) | B6: 2
A7: WT (in) | B7: 0.154
A8: MOP (psi) | B8: 200
A9: Stress ratio R | B9: 0.92
A10: Pressure cycles/yr | B10: 10000
A11: Avg crack depth (in) | B11: 0.035
A12: Steel grade | B12: API 5L B
A13: Base annual leak rate (/hr) | B13: =Global_Assumptions!$B$53
A14: Base annual burst rate (/hr) | B14: =Global_Assumptions!$B$54
A16: Blend % | B16: FCGR mult | C16: Leak rate H2 (/hr) | D16: Burst rate H2 (/hr) | E16: PoF leak 20yr | F16: PoF burst 20yr | G16: Combined PoF 20yr
A17: 0 | B17: =VLOOKUP(A17,Global_Assumptions!$A$72:$B$79,2,FALSE()) | C17: =$B$13*B17 | D17: =$B$14*B17 | E17: =1-EXP(-C17*8760*Global_Assumptions!$B$52) | F17: =1-EXP(-D17*8760*Global_Assumptions!$B$52) | G17: =1-(1-E17)*(1-F17)
A18: 5 | B18: =VLOOKUP(A18,Global_Assumptions!$A$72:$B$79,2,FALSE()) | C18: =$B$13*B18 | D18: =$B$14*B18 | E18: =1-EXP(-C18*8760*Global_Assumptions!$B$52) | F18: =1-EXP(-D18*8760*Global_Assumptions!$B$52) | G18: =1-(1-E18)*(1-F18)
A19: 10 | B19: =VLOOKUP(A19,Global_Assumptions!$A$72:$B$79,2,FALSE()) | C19: =$B$13*B19 | D19: =$B$14*B19 | E19: =1-EXP(-C19*8760*Global_Assumptions!$B$52) | F19: =1-EXP(-D19*8760*Global_Assumptions!$B$52) | G19: =1-(1-E19)*(1-F19)
A20: 20 | B20: =VLOOKUP(A20,Global_Assumptions!$A$72:$B$79,2,FALSE()) | C20: =$B$13*B20 | D20: =$B$14*B20 | E20: =1-EXP(-C20*8760*Global_Assumptions!$B$52) | F20: =1-EXP(-D20*8760*Global_Assumptions!$B$52) | G20: =1-(1-E20)*(1-F20)
A21: 30 | B21: =VLOOKUP(A21,Global_Assumptions!$A$72:$B$79,2,FALSE()) | C21: =$B$13*B21 | D21: =$B$14*B21 | E21: =1-EXP(-C21*8760*Global_Assumptions!$B$52) | F21: =1-EXP(-D21*8760*Global_Assumptions!$B$52) | G21: =1-(1-E21)*(1-F21)
A22: 50 | B22: =VLOOKUP(A22,Global_Assumptions!$A$72:$B$79,2,FALSE()) | C22: =$B$13*B22 | D22: =$B$14*B22 | E22: =1-EXP(-C22*8760*Global_Assumptions!$B$52) | F22: =1-EXP(-D22*8760*Global_Assumptions!$B$52) | G22: =1-(1-E22)*(1-F22)
A23: 75 | B23: =VLOOKUP(A23,Global_Assumptions!$A$72:$B$79,2,FALSE()) | C23: =$B$13*B23 | D23: =$B$14*B23 | E23: =1-EXP(-C23*8760*Global_Assumptions!$B$52) | F23: =1-EXP(-D23*8760*Global_Assumptions!$B$52) | G23: =1-(1-E23)*(1-F23)
A24: 100 | B24: =VLOOKUP(A24,Global_Assumptions!$A$72:$B$79,2,FALSE()) | C24: =$B$13*B24 | D24: =$B$14*B24 | E24: =1-EXP(-C24*8760*Global_Assumptions!$B$52) | F24: =1-EXP(-D24*8760*Global_Assumptions!$B$52) | G24: =1-(1-E24)*(1-F24)

Sheet PoF_Summary
A1: COMPONENT-LEVEL 20-YEAR PoF SUMMARY (harmonized thresholds)
A2: Series-logic fault tree. PoF calibrated to UCI component Bayesian-network models (100k MC) + UCI turbine model. Amber/red flags from Global_Assumptions.
A3: Component | B3: Count | C3: Approach | D3: PoF20 base | E3: PoF20 H2 | F3: Flag | G3: Dominant hydrogen effect
A4: Delivery Lateral Pipe | B4: 1 | C4: Fracture-mechanics fatigue | D4: =Pipe_Integrity!G17 | E4: =Pipe_Integrity!$G$20 | F4: =IF(E4>=Global_Assumptions!$B$56,"RED",IF(E4>=Global_Assumptions!$B$55,"AMBER","OK")) | G4: FCGR up ~1 order of magnitude
A5: Injection/Isolation Valve | B5: 3 | C5: UCI valve BN (100k MC) | D5: 0.6189 | E5: 0.6795 | F5: =IF(E5>=Global_Assumptions!$B$56,"RED",IF(E5>=Global_Assumptions!$B$55,"AMBER","OK")) | G5: EL & delayed-op amplified
A6: Pressure Regulator | B6: 1 | C6: UCI regulator BN (100k MC) | D6: 0.8537 | E6: 0.8716 | F6: =IF(E6>=Global_Assumptions!$B$56,"RED",IF(E6>=Global_Assumptions!$B$55,"AMBER","OK")) | G6: Seal/diaphragm compatibility
A7: Meter | B7: 1 | C7: NGRMS MTTF (instrument) | D7: =1-EXP(-SUMIF(Failure_Rates!$A$4:$A$15,A7,Failure_Rates!$D$4:$D$15)*8760*Global_Assumptions!$B$52) | E7: =1-EXP(-SUMIF(Failure_Rates!$A$4:$A$15,A7,Failure_Rates!$F$4:$F$15)*8760*Global_Assumptions!$B$52) | F7: =IF(E7>=Global_Assumptions!$B$56,"RED",IF(E7>=Global_Assumptions!$B$55,"AMBER","OK")) | G7: Gas-property change affects calibration
A8: Buffer Storage | B8: 1 | C8: Screening PoF (vessel) | D8: 0.05 | E8: 0.07 | F8: =IF(E8>=Global_Assumptions!$B$56,"RED",IF(E8>=Global_Assumptions!$B$55,"AMBER","OK")) | G8: Permeation; embrittlement of liner
A9: Capstone C200 Microturbine | B9: 1 | C9: Screening PoF (recuperated) | D9: 0.79 | E9: 0.79 | F9: =IF(E9>=Global_Assumptions!$B$56,"RED",IF(E9>=Global_Assumptions!$B$55,"AMBER","OK")) | G9: Flashback; injector wear
A10: Recuperator Heat Exchanger | B10: 1 | C10: UCI heat_exchanger BN (100k MC) | D10: 0.7205 | E10: 0.7406 | F10: =IF(E10>=Global_Assumptions!$B$56,"RED",IF(E10>=Global_Assumptions!$B$55,"AMBER","OK")) | G10: H2 permeation / HTHA screening

Sheet Inspection_Maint
A1: INSPECTION & MAINTENANCE PLAN (common-pipe unit costs harmonized)
A2: Pipe inspection unit costs come from Global_Assumptions (normal vs purpose-built), identical across cases.
A3: Component | B3: Inspection (type & frequency) | C3: Maintenance | D3: Unit cost basis | E3: Annual cost ($)
A4: Delivery Lateral Pipe | B4: Patrol + ILI (>=1/7yr); leak survey | C4: Condition-based (clamp/sleeve/replace) | D4: ="$"&TEXT(Global_Assumptions!$B$58,"#,##0")&"/mi (normal)" | E4: =Global_Assumptions!$B$58*1
A5: Injection/Isolation Valve | B5: Functional/leak test >=1/yr | C5: Lubricate; reseat; replace seals | D5: component-scale (vendor) | E5: 15000
A6: Pressure Regulator | B6: Visual monthly; functional 2/yr | C6: Pilot adjust; preventive 2/yr | D6: component-scale (vendor) | E6: 4000
A7: Meter | B7: Continuous remote monitoring | C7: Calibration/recalibration | D7: component-scale (vendor) | E7: 3000
A8: Buffer Storage | B8: Visual + relief-valve test | C8: Pressure-vessel inspection | D8: component-scale (vendor) | E8: 8000
A9: Capstone C200 Microturbine | B9: OEM service 1/yr | C9: Injector + recuperator service | D9: component-scale (vendor) | E9: 53000
A10: Recuperator Heat Exchanger | B10: Tube inspection + leak test | C10: Clean / re-tube | D10: component-scale (vendor) | E10: 44000
A12: Inspection scenario (per mile)
A13: Scenario | B13: $/mile/yr
A14: Normal (existing) pipeline | B14: =Global_Assumptions!$B$58
A15: Purpose-built (less frequent) | B15: =Global_Assumptions!$B$59

Sheet Blend_Properties
A1: BLEND PROPERTIES & H2 DEMAND — UCI Microturbine
A2: Energy fraction E=v·k/(v·k+1−v); flow factor=1/((1−v)+v·k); demand=fuel·E/gj_kg. k, gj_kg from Global.
A3: Baseline fuel energy (GJ/yr) | B3: 14100
A4: Baseline fossil CO2 (t/yr) | B4: =B3*0.0561
A5: Blend % (vol) | B5: H2 energy frac | C5: Flow factor | D5: FCGR mult | E5: kg basis | F5: H2 demand (kg/yr) | G5: CO2 avoided (t/yr) | H5: Residual CO2 (t/yr)
A6: 0 | B6: =((A6/100)*Global_Assumptions!$B$26)/(((A6/100)*Global_Assumptions!$B$26)+(1-(A6/100))) | C6: =1/((1-(A6/100))+(A6/100)*Global_Assumptions!$B$26) | D6: =VLOOKUP(A6,Global_Assumptions!$A$72:$B$79,2,FALSE()) | F6: =$B$3*B6/Global_Assumptions!$B$25 | G6: =$B$4*B6 | H6: =$B$4*(1-B6)
A7: 5 | B7: =((A7/100)*Global_Assumptions!$B$26)/(((A7/100)*Global_Assumptions!$B$26)+(1-(A7/100))) | C7: =1/((1-(A7/100))+(A7/100)*Global_Assumptions!$B$26) | D7: =VLOOKUP(A7,Global_Assumptions!$A$72:$B$79,2,FALSE()) | F7: =$B$3*B7/Global_Assumptions!$B$25 | G7: =$B$4*B7 | H7: =$B$4*(1-B7)
A8: 10 | B8: =((A8/100)*Global_Assumptions!$B$26)/(((A8/100)*Global_Assumptions!$B$26)+(1-(A8/100))) | C8: =1/((1-(A8/100))+(A8/100)*Global_Assumptions!$B$26) | D8: =VLOOKUP(A8,Global_Assumptions!$A$72:$B$79,2,FALSE()) | F8: =$B$3*B8/Global_Assumptions!$B$25 | G8: =$B$4*B8 | H8: =$B$4*(1-B8)
A9: 20 | B9: =((A9/100)*Global_Assumptions!$B$26)/(((A9/100)*Global_Assumptions!$B$26)+(1-(A9/100))) | C9: =1/((1-(A9/100))+(A9/100)*Global_Assumptions!$B$26) | D9: =VLOOKUP(A9,Global_Assumptions!$A$72:$B$79,2,FALSE()) | F9: =$B$3*B9/Global_Assumptions!$B$25 | G9: =$B$4*B9 | H9: =$B$4*(1-B9)
A10: 30 | B10: =((A10/100)*Global_Assumptions!$B$26)/(((A10/100)*Global_Assumptions!$B$26)+(1-(A10/100))) | C10: =1/((1-(A10/100))+(A10/100)*Global_Assumptions!$B$26) | D10: =VLOOKUP(A10,Global_Assumptions!$A$72:$B$79,2,FALSE()) | F10: =$B$3*B10/Global_Assumptions!$B$25 | G10: =$B$4*B10 | H10: =$B$4*(1-B10)
A11: 50 | B11: =((A11/100)*Global_Assumptions!$B$26)/(((A11/100)*Global_Assumptions!$B$26)+(1-(A11/100))) | C11: =1/((1-(A11/100))+(A11/100)*Global_Assumptions!$B$26) | D11: =VLOOKUP(A11,Global_Assumptions!$A$72:$B$79,2,FALSE()) | F11: =$B$3*B11/Global_Assumptions!$B$25 | G11: =$B$4*B11 | H11: =$B$4*(1-B11)
A12: 75 | B12: =((A12/100)*Global_Assumptions!$B$26)/(((A12/100)*Global_Assumptions!$B$26)+(1-(A12/100))) | C12: =1/((1-(A12/100))+(A12/100)*Global_Assumptions!$B$26) | D12: =VLOOKUP(A12,Global_Assumptions!$A$72:$B$79,2,FALSE()) | F12: =$B$3*B12/Global_Assumptions!$B$25 | G12: =$B$4*B12 | H12: =$B$4*(1-B12)
A13: 100 | B13: =((A13/100)*Global_Assumptions!$B$26)/(((A13/100)*Global_Assumptions!$B$26)+(1-(A13/100))) | C13: =1/((1-(A13/100))+(A13/100)*Global_Assumptions!$B$26) | D13: =VLOOKUP(A13,Global_Assumptions!$A$72:$B$79,2,FALSE()) | F13: =$B$3*B13/Global_Assumptions!$B$25 | G13: =$B$4*B13 | H13: =$B$4*(1-B13)

Sheet TEA_CAPEX
A1: CAPEX MODEL — UCI Microturbine
A2: Unit costs from Global_Assumptions. Pipe length is system length (transmission) or lateral distance (end-use).
A3: Pipeline option | B3: $/mile | C3: Total ($) | D3: Basis
A4: New purpose-built | B4: =Global_Assumptions!$B$44*Global_Assumptions!$B$46*1000000 | C4: =B4*1 | D4: new_pipe×premium [P3][R5]
A5: Repurposed (retrofit) | B5: =Global_Assumptions!$B$44*Global_Assumptions!$B$45*1000000 | C5: =B5*1 | D5: new_pipe×retrofit_factor [P3]
A7: Injection / compression / storage
A8: Item | B8: Value | C8: Unit | D8: Basis
A9: Injection+metering+control skid | B9: =Global_Assumptions!$B$47*1000000 | C9: $ | D9: [P2]
A10: Storage (buffer) | B10: =Blend_Properties!$F$13/365*Global_Assumptions!$B$49*Global_Assumptions!$B$48 | C10: $ @100% demand | D10: storage_days×kg [P2]
A11: Compressor unit CAPEX | B11: 0 | C11: $/unit @100% | D11: comp_capex×MW
A13: CCS & NCD (carbon)
A14: Item | B14: $/tCO2
A15: CCS industrial | B15: =Global_Assumptions!$B$32
A16: CCS power generation | B16: =Global_Assumptions!$B$33
A17: CCS DAC | B17: =Global_Assumptions!$B$34
A18: NCD base / slope | B18: =Global_Assumptions!$B$35&" / "&Global_Assumptions!$B$36

Sheet TEA_Hydraulics
A1: HYDRAULICS & COMPRESSOR COUNT — UCI Microturbine
A2: N_comp = MAX(1, CEILING(distance/spacing × flow_factor)). Spacing from Global_Assumptions.
A3: Near distance (mi) | B3: 1 | D3: Far distance (mi) | E3: 100
A4: Blend % | B4: Flow factor | C4: Compressors near | D4: Compressors far | E4: Comp power near (MW) | F4: Comp energy (kWh/kg)
A5: 0 | B5: =Blend_Properties!$C$6 | C5: =MAX(1,CEILING($B$3/Global_Assumptions!$B$42*B5,1)) | D5: =MAX(1,CEILING($E$3/Global_Assumptions!$B$42*B5,1)) | E5: =Blend_Properties!$F$6*Global_Assumptions!$B$38/8760/1000 | F5: =Global_Assumptions!$B$38
A6: 5 | B6: =Blend_Properties!$C$7 | C6: =MAX(1,CEILING($B$3/Global_Assumptions!$B$42*B6,1)) | D6: =MAX(1,CEILING($E$3/Global_Assumptions!$B$42*B6,1)) | E6: =Blend_Properties!$F$7*Global_Assumptions!$B$38/8760/1000 | F6: =Global_Assumptions!$B$38
A7: 10 | B7: =Blend_Properties!$C$8 | C7: =MAX(1,CEILING($B$3/Global_Assumptions!$B$42*B7,1)) | D7: =MAX(1,CEILING($E$3/Global_Assumptions!$B$42*B7,1)) | E7: =Blend_Properties!$F$8*Global_Assumptions!$B$38/8760/1000 | F7: =Global_Assumptions!$B$38
A8: 20 | B8: =Blend_Properties!$C$9 | C8: =MAX(1,CEILING($B$3/Global_Assumptions!$B$42*B8,1)) | D8: =MAX(1,CEILING($E$3/Global_Assumptions!$B$42*B8,1)) | E8: =Blend_Properties!$F$9*Global_Assumptions!$B$38/8760/1000 | F8: =Global_Assumptions!$B$38
A9: 30 | B9: =Blend_Properties!$C$10 | C9: =MAX(1,CEILING($B$3/Global_Assumptions!$B$42*B9,1)) | D9: =MAX(1,CEILING($E$3/Global_Assumptions!$B$42*B9,1)) | E9: =Blend_Properties!$F$10*Global_Assumptions!$B$38/8760/1000 | F9: =Global_Assumptions!$B$38
A10: 50 | B10: =Blend_Properties!$C$11 | C10: =MAX(1,CEILING($B$3/Global_Assumptions!$B$42*B10,1)) | D10: =MAX(1,CEILING($E$3/Global_Assumptions!$B$42*B10,1)) | E10: =Blend_Properties!$F$11*Global_Assumptions!$B$38/8760/1000 | F10: =Global_Assumptions!$B$38
A11: 75 | B11: =Blend_Properties!$C$12 | C11: =MAX(1,CEILING($B$3/Global_Assumptions!$B$42*B11,1)) | D11: =MAX(1,CEILING($E$3/Global_Assumptions!$B$42*B11,1)) | E11: =Blend_Properties!$F$12*Global_Assumptions!$B$38/8760/1000 | F11: =Global_Assumptions!$B$38
A12: 100 | B12: =Blend_Properties!$C$13 | C12: =MAX(1,CEILING($B$3/Global_Assumptions!$B$42*B12,1)) | D12: =MAX(1,CEILING($E$3/Global_Assumptions!$B$42*B12,1)) | E12: =Blend_Properties!$F$13*Global_Assumptions!$B$38/8760/1000 | F12: =Global_Assumptions!$B$38

Sheet TEA_OPEX_Perf
A1: OPEX & TECHNICAL PERFORMANCE — UCI Microturbine
A2: Energy fraction, flow factor & demand from Blend_Properties; inspection from Global I&M unit cost × miles.
A3: Blend % | B3: Energy frac | C3: Delivery eff. | D3: Compression ($/yr) | E3: Inspection ($/yr) | F3: Leakage make-up (kg/yr) | G3: Throughput flag
A4: 0 | B4: =Blend_Properties!$B$6 | C4: =1-(Global_Assumptions!$B$38/Global_Assumptions!$B$24) | D4: =Blend_Properties!$F$6*Global_Assumptions!$B$38*Global_Assumptions!$B$19 | E4: =Global_Assumptions!$B$58*1 | F4: =Blend_Properties!$F$6*Global_Assumptions!$B$29 | G4: =IF(Blend_Properties!$C$6>3,"check capacity","OK")
A5: 5 | B5: =Blend_Properties!$B$7 | C5: =1-(Global_Assumptions!$B$38/Global_Assumptions!$B$24) | D5: =Blend_Properties!$F$7*Global_Assumptions!$B$38*Global_Assumptions!$B$19 | E5: =Global_Assumptions!$B$58*1 | F5: =Blend_Properties!$F$7*Global_Assumptions!$B$29 | G5: =IF(Blend_Properties!$C$7>3,"check capacity","OK")
A6: 10 | B6: =Blend_Properties!$B$8 | C6: =1-(Global_Assumptions!$B$38/Global_Assumptions!$B$24) | D6: =Blend_Properties!$F$8*Global_Assumptions!$B$38*Global_Assumptions!$B$19 | E6: =Global_Assumptions!$B$58*1 | F6: =Blend_Properties!$F$8*Global_Assumptions!$B$29 | G6: =IF(Blend_Properties!$C$8>3,"check capacity","OK")
A7: 20 | B7: =Blend_Properties!$B$9 | C7: =1-(Global_Assumptions!$B$38/Global_Assumptions!$B$24) | D7: =Blend_Properties!$F$9*Global_Assumptions!$B$38*Global_Assumptions!$B$19 | E7: =Global_Assumptions!$B$58*1 | F7: =Blend_Properties!$F$9*Global_Assumptions!$B$29 | G7: =IF(Blend_Properties!$C$9>3,"check capacity","OK")
A8: 30 | B8: =Blend_Properties!$B$10 | C8: =1-(Global_Assumptions!$B$38/Global_Assumptions!$B$24) | D8: =Blend_Properties!$F$10*Global_Assumptions!$B$38*Global_Assumptions!$B$19 | E8: =Global_Assumptions!$B$58*1 | F8: =Blend_Properties!$F$10*Global_Assumptions!$B$29 | G8: =IF(Blend_Properties!$C$10>3,"check capacity","OK")
A9: 50 | B9: =Blend_Properties!$B$11 | C9: =1-(Global_Assumptions!$B$38/Global_Assumptions!$B$24) | D9: =Blend_Properties!$F$11*Global_Assumptions!$B$38*Global_Assumptions!$B$19 | E9: =Global_Assumptions!$B$58*1 | F9: =Blend_Properties!$F$11*Global_Assumptions!$B$29 | G9: =IF(Blend_Properties!$C$11>3,"check capacity","OK")
A10: 75 | B10: =Blend_Properties!$B$12 | C10: =1-(Global_Assumptions!$B$38/Global_Assumptions!$B$24) | D10: =Blend_Properties!$F$12*Global_Assumptions!$B$38*Global_Assumptions!$B$19 | E10: =Global_Assumptions!$B$58*1 | F10: =Blend_Properties!$F$12*Global_Assumptions!$B$29 | G10: =IF(Blend_Properties!$C$12>3,"check capacity","OK")
A11: 100 | B11: =Blend_Properties!$B$13 | C11: =1-(Global_Assumptions!$B$38/Global_Assumptions!$B$24) | D11: =Blend_Properties!$F$13*Global_Assumptions!$B$38*Global_Assumptions!$B$19 | E11: =Global_Assumptions!$B$58*1 | F11: =Blend_Properties!$F$13*Global_Assumptions!$B$29 | G11: =IF(Blend_Properties!$C$13>3,"check capacity","OK")

Sheet TEA_Network
A1: NETWORK-BASED COST ALLOCATION — UCI Microturbine
A2: Production / transmission / delivery split. Validated pipeline anchor from Reed 2024 [P2].
A3: Cost layer | B3: $/kg | C3: Output metric | D3: Basis
A4: Production (RH2 commodity) | B4: =Global_Assumptions!$B$13 | C4: $/kg produced | D4: [P1][P2]
A5: Transmission (pipeline+compression) | B5: 0.71 | C5: $/kg transported | D5: [P2] Reed 2024
A6: Local delivery (skid+storage) | B6: 0.11 | C6: $/kg delivered | D6: [P2]
A7: End-use integration | B7: 0.04 | C7: $/MWh useful | D7: [P2]
A8: Total delivered, $/kg (excl. $/MWh integration) | B8: =SUM(B4:B6) | C8: $/kg | D8: validated $2.85/kg [P2]
A10: Alternative delivery pathways ($/kg)
A11: Pathway | B11: $/kg | C11: Type | D11: Source
A12: Pipeline (direct) | B12: 2.85 | C12: direct | D12: [P2]
A13: Cryo-tanker (direct) | B13: 3.98 | C13: direct | D13: [P2]
A14: On-site electrolysis | B14: 3.65 | C14: on-site | D14: [P2]
A15: Ammonia carrier | B15: 5 | C15: carrier | D15: placeholder
A16: LOHC carrier | B16: 4.5 | C16: carrier | D16: placeholder

Sheet TEA_Levelized
A1: LEVELIZED METRICS — UCI Microturbine
A2: LCOH = RH2 + (CCRF·CAPEX + OPEX)/(demand·availability). Pulls scenario totals from Scenario_Results (near retrofit).
A3: Blend % | B3: LCOH near ($/kg) | C3: LCOH far ($/kg) | D3: LCOH w/ 45V (if eligible) ($/kg) | E3: $/tCO2e avoided | F3: Lev. capture ($/tCO2) | G3: CO2 avoided (t/yr)
A4: 0 | B4: =IF($A4=0,"N/A",Scenario_Results!K4) | C4: =IF($A4=0,"N/A",Scenario_Results!K5) | D4: =IF($A4=0,"N/A",B4+Global_Assumptions!$B$21) | E4: =IF($A4=0,"N/A",Scenario_Results!M4) | F4: =Scenario_Results!N4 | G4: =Blend_Properties!$G$6
A5: 5 | B5: =Scenario_Results!K7 | C5: =Scenario_Results!K8 | D5: =B5+Global_Assumptions!$B$21 | E5: =Scenario_Results!M7 | F5: =Scenario_Results!N7 | G5: =Blend_Properties!$G$7
A6: 10 | B6: =Scenario_Results!K10 | C6: =Scenario_Results!K11 | D6: =B6+Global_Assumptions!$B$21 | E6: =Scenario_Results!M10 | F6: =Scenario_Results!N10 | G6: =Blend_Properties!$G$8
A7: 20 | B7: =Scenario_Results!K13 | C7: =Scenario_Results!K14 | D7: =B7+Global_Assumptions!$B$21 | E7: =Scenario_Results!M13 | F7: =Scenario_Results!N13 | G7: =Blend_Properties!$G$9
A8: 30 | B8: =Scenario_Results!K16 | C8: =Scenario_Results!K17 | D8: =B8+Global_Assumptions!$B$21 | E8: =Scenario_Results!M16 | F8: =Scenario_Results!N16 | G8: =Blend_Properties!$G$10
A9: 50 | B9: =Scenario_Results!K19 | C9: =Scenario_Results!K20 | D9: =B9+Global_Assumptions!$B$21 | E9: =Scenario_Results!M19 | F9: =Scenario_Results!N19 | G9: =Blend_Properties!$G$11
A10: 75 | B10: =Scenario_Results!K22 | C10: =Scenario_Results!K23 | D10: =B10+Global_Assumptions!$B$21 | E10: =Scenario_Results!M22 | F10: =Scenario_Results!N22 | G10: =Blend_Properties!$G$12
A11: 100 | B11: =Scenario_Results!K25 | C11: =Scenario_Results!K26 | D11: =B11+Global_Assumptions!$B$21 | E11: =Scenario_Results!M25 | F11: =Scenario_Results!N25 | G11: =Blend_Properties!$G$13

Sheet TEA_Pathways
A1: COMPARATIVE PATHWAYS (high level) — UCI Microturbine
A2: Retrofit vs new; blend vs full; direct vs carrier. Paper-sourced where available; carriers are placeholders.
A3: Comparison | B3: Value | C3: Unit | D3: Note
A4: Retrofit pipeline | B4: =TEA_CAPEX!C5 | C4: $ total | D4: 20% of new [P3]
A5: New purpose-built pipeline | B5: =TEA_CAPEX!C4 | C5: $ total | D5: new×premium [R5]
A6: Blend 20% (near) LCOH | B6: =TEA_Levelized!B7 | C6: $/kg | D6: moderate decarbonization
A7: Full 100% (near) LCOH | B7: =TEA_Levelized!B11 | C7: $/kg | D7: max decarbonization
A8: Pipeline (direct) | B8: =TEA_Network!B14 | C8: $/kg | D8: [P2]
A9: Cryo-tanker (direct) | B9: =TEA_Network!B15 | C9: $/kg | D9: [P2]
A10: On-site electrolysis | B10: =TEA_Network!B16 | C10: $/kg | D10: [P2]
A11: Ammonia carrier | B11: =TEA_Network!B17 | C11: $/kg | D11: placeholder
A12: LOHC carrier | B12: =TEA_Network!B18 | C12: $/kg | D12: placeholder

Sheet Scenario_Results
A1: UNIFIED SCENARIO RESULTS — UCI Microturbine (formula-driven)
A2: Blend × distance × pathway. All columns computed from Global_Assumptions + Blend_Properties + Hydraulics.
A3: Blend% | B3: Dist(mi) | C3: Pathway | D3: H2 (kg/yr) | E3: Compr. | F3: Pipe CAPEX($) | G3: Comp CAPEX($) | H3: Skid+Stor($) | I3: Ann.CAPEX($) | J3: Ann.OPEX($) | K3: LCOH($/kg) | L3: CCS($/yr) | M3: $/tCO2e | N3: Lev.cap($/tCO2)
A4: 0 | B4: =TEA_Hydraulics!$B$3 | C4: retrofit | D4: =Blend_Properties!$F$6 | E4: =TEA_Hydraulics!C5 | F4: =(Global_Assumptions!$B$44*Global_Assumptions!$B$45*1000000)*TEA_Hydraulics!$B$3 | G4: 0 | H4: =Global_Assumptions!$B$47*1000000+Blend_Properties!$F$6/365*Global_Assumptions!$B$49*Global_Assumptions!$B$48 | I4: =(F4+G4+H4)*Global_Assumptions!$B$5 | J4: =Blend_Properties!$F$6*Global_Assumptions!$B$38*Global_Assumptions!$B$19 + G4*Global_Assumptions!$B$41 + F4*Global_Assumptions!$B$50 + Global_Assumptions!$B$58*TEA_Hydraulics!$B$3 + Blend_Properties!$H$6*Global_Assumptions!$B$33*Global_Assumptions!$B$31 | K4: =IF(D4>0,Global_Assumptions!$B$13+(I4+J4)/(D4*Global_Assumptions!$B$11),0) | L4: =Blend_Properties!$H$6*Global_Assumptions!$B$33*Global_Assumptions!$B$31 | M4: =IF(Blend_Properties!$G$6>0,(I4+J4)/Blend_Properties!$G$6,0) | N4: =Global_Assumptions!$B$33
A5: 0 | B5: =TEA_Hydraulics!$E$3 | C5: retrofit | D5: =Blend_Properties!$F$6 | E5: =TEA_Hydraulics!D5 | F5: =(Global_Assumptions!$B$44*Global_Assumptions!$B$45*1000000)*TEA_Hydraulics!$E$3 | G5: =E5*Global_Assumptions!$B$39*1000000*(Blend_Properties!$F$6*Global_Assumptions!$B$38/8760/1000) | H5: =Global_Assumptions!$B$47*1000000+Blend_Properties!$F$6/365*Global_Assumptions!$B$49*Global_Assumptions!$B$48 | I5: =(F5+G5+H5)*Global_Assumptions!$B$5 | J5: =Blend_Properties!$F$6*Global_Assumptions!$B$38*Global_Assumptions!$B$19 + G5*Global_Assumptions!$B$41 + F5*Global_Assumptions!$B$50 + Global_Assumptions!$B$58*TEA_Hydraulics!$E$3 + Blend_Properties!$H$6*Global_Assumptions!$B$33*Global_Assumptions!$B$31 | K5: =IF(D5>0,Global_Assumptions!$B$13+(I5+J5)/(D5*Global_Assumptions!$B$11),0) | L5: =Blend_Properties!$H$6*Global_Assumptions!$B$33*Global_Assumptions!$B$31 | M5: =IF(Blend_Properties!$G$6>0,(I5+J5)/Blend_Properties!$G$6,0) | N5: =Global_Assumptions!$B$33
A6: 0 | B6: =TEA_Hydraulics!$E$3 | C6: new | D6: =Blend_Properties!$F$6 | E6: =TEA_Hydraulics!D5 | F6: =(Global_Assumptions!$B$44*Global_Assumptions!$B$46*1000000)*TEA_Hydraulics!$E$3 | G6: =E6*Global_Assumptions!$B$39*1000000*(Blend_Properties!$F$6*Global_Assumptions!$B$38/8760/1000) | H6: =Global_Assumptions!$B$47*1000000+Blend_Properties!$F$6/365*Global_Assumptions!$B$49*Global_Assumptions!$B$48 | I6: =(F6+G6+H6)*Global_Assumptions!$B$5 | J6: =Blend_Properties!$F$6*Global_Assumptions!$B$38*Global_Assumptions!$B$19 + G6*Global_Assumptions!$B$41 + F6*Global_Assumptions!$B$50 + Global_Assumptions!$B$59*TEA_Hydraulics!$E$3 + Blend_Properties!$H$6*Global_Assumptions!$B$33*Global_Assumptions!$B$31 | K6: =IF(D6>0,Global_Assumptions!$B$13+(I6+J6)/(D6*Global_Assumptions!$B$11),0) | L6: =Blend_Properties!$H$6*Global_Assumptions!$B$33*Global_Assumptions!$B$31 | M6: =IF(Blend_Properties!$G$6>0,(I6+J6)/Blend_Properties!$G$6,0) | N6: =Global_Assumptions!$B$33
A7: 5 | B7: =TEA_Hydraulics!$B$3 | C7: retrofit | D7: =Blend_Properties!$F$7 | E7: =TEA_Hydraulics!C6 | F7: =(Global_Assumptions!$B$44*Global_Assumptions!$B$45*1000000)*TEA_Hydraulics!$B$3 | G7: 0 | H7: =Global_Assumptions!$B$47*1000000+Blend_Properties!$F$7/365*Global_Assumptions!$B$49*Global_Assumptions!$B$48 | I7: =(F7+G7+H7)*Global_Assumptions!$B$5 | J7: =Blend_Properties!$F$7*Global_Assumptions!$B$38*Global_Assumptions!$B$19 + G7*Global_Assumptions!$B$41 + F7*Global_Assumptions!$B$50 + Global_Assumptions!$B$58*TEA_Hydraulics!$B$3 + Blend_Properties!$H$7*Global_Assumptions!$B$33*Global_Assumptions!$B$31 | K7: =IF(D7>0,Global_Assumptions!$B$13+(I7+J7)/(D7*Global_Assumptions!$B$11),0) | L7: =Blend_Properties!$H$7*Global_Assumptions!$B$33*Global_Assumptions!$B$31 | M7: =IF(Blend_Properties!$G$7>0,(I7+J7)/Blend_Properties!$G$7,0) | N7: =Global_Assumptions!$B$33
A8: 5 | B8: =TEA_Hydraulics!$E$3 | C8: retrofit | D8: =Blend_Properties!$F$7 | E8: =TEA_Hydraulics!D6 | F8: =(Global_Assumptions!$B$44*Global_Assumptions!$B$45*1000000)*TEA_Hydraulics!$E$3 | G8: =E8*Global_Assumptions!$B$39*1000000*(Blend_Properties!$F$7*Global_Assumptions!$B$38/8760/1000) | H8: =Global_Assumptions!$B$47*1000000+Blend_Properties!$F$7/365*Global_Assumptions!$B$49*Global_Assumptions!$B$48 | I8: =(F8+G8+H8)*Global_Assumptions!$B$5 | J8: =Blend_Properties!$F$7*Global_Assumptions!$B$38*Global_Assumptions!$B$19 + G8*Global_Assumptions!$B$41 + F8*Global_Assumptions!$B$50 + Global_Assumptions!$B$58*TEA_Hydraulics!$E$3 + Blend_Properties!$H$7*Global_Assumptions!$B$33*Global_Assumptions!$B$31 | K8: =IF(D8>0,Global_Assumptions!$B$13+(I8+J8)/(D8*Global_Assumptions!$B$11),0) | L8: =Blend_Properties!$H$7*Global_Assumptions!$B$33*Global_Assumptions!$B$31 | M8: =IF(Blend_Properties!$G$7>0,(I8+J8)/Blend_Properties!$G$7,0) | N8: =Global_Assumptions!$B$33
A9: 5 | B9: =TEA_Hydraulics!$E$3 | C9: new | D9: =Blend_Properties!$F$7 | E9: =TEA_Hydraulics!D6 | F9: =(Global_Assumptions!$B$44*Global_Assumptions!$B$46*1000000)*TEA_Hydraulics!$E$3 | G9: =E9*Global_Assumptions!$B$39*1000000*(Blend_Properties!$F$7*Global_Assumptions!$B$38/8760/1000) | H9: =Global_Assumptions!$B$47*1000000+Blend_Properties!$F$7/365*Global_Assumptions!$B$49*Global_Assumptions!$B$48 | I9: =(F9+G9+H9)*Global_Assumptions!$B$5 | J9: =Blend_Properties!$F$7*Global_Assumptions!$B$38*Global_Assumptions!$B$19 + G9*Global_Assumptions!$B$41 + F9*Global_Assumptions!$B$50 + Global_Assumptions!$B$59*TEA_Hydraulics!$E$3 + Blend_Properties!$H$7*Global_Assumptions!$B$33*Global_Assumptions!$B$31 | K9: =IF(D9>0,Global_Assumptions!$B$13+(I9+J9)/(D9*Global_Assumptions!$B$11),0) | L9: =Blend_Properties!$H$7*Global_Assumptions!$B$33*Global_Assumptions!$B$31 | M9: =IF(Blend_Properties!$G$7>0,(I9+J9)/Blend_Properties!$G$7,0) | N9: =Global_Assumptions!$B$33
A10: 10 | B10: =TEA_Hydraulics!$B$3 | C10: retrofit | D10: =Blend_Properties!$F$8 | E10: =TEA_Hydraulics!C7 | F10: =(Global_Assumptions!$B$44*Global_Assumptions!$B$45*1000000)*TEA_Hydraulics!$B$3 | G10: 0 | H10: =Global_Assumptions!$B$47*1000000+Blend_Properties!$F$8/365*Global_Assumptions!$B$49*Global_Assumptions!$B$48 | I10: =(F10+G10+H10)*Global_Assumptions!$B$5 | J10: =Blend_Properties!$F$8*Global_Assumptions!$B$38*Global_Assumptions!$B$19 + G10*Global_Assumptions!$B$41 + F10*Global_Assumptions!$B$50 + Global_Assumptions!$B$58*TEA_Hydraulics!$B$3 + Blend_Properties!$H$8*Global_Assumptions!$B$33*Global_Assumptions!$B$31 | K10: =IF(D10>0,Global_Assumptions!$B$13+(I10+J10)/(D10*Global_Assumptions!$B$11),0) | L10: =Blend_Properties!$H$8*Global_Assumptions!$B$33*Global_Assumptions!$B$31 | M10: =IF(Blend_Properties!$G$8>0,(I10+J10)/Blend_Properties!$G$8,0) | N10: =Global_Assumptions!$B$33
A11: 10 | B11: =TEA_Hydraulics!$E$3 | C11: retrofit | D11: =Blend_Properties!$F$8 | E11: =TEA_Hydraulics!D7 | F11: =(Global_Assumptions!$B$44*Global_Assumptions!$B$45*1000000)*TEA_Hydraulics!$E$3 | G11: =E11*Global_Assumptions!$B$39*1000000*(Blend_Properties!$F$8*Global_Assumptions!$B$38/8760/1000) | H11: =Global_Assumptions!$B$47*1000000+Blend_Properties!$F$8/365*Global_Assumptions!$B$49*Global_Assumptions!$B$48 | I11: =(F11+G11+H11)*Global_Assumptions!$B$5 | J11: =Blend_Properties!$F$8*Global_Assumptions!$B$38*Global_Assumptions!$B$19 + G11*Global_Assumptions!$B$41 + F11*Global_Assumptions!$B$50 + Global_Assumptions!$B$58*TEA_Hydraulics!$E$3 + Blend_Properties!$H$8*Global_Assumptions!$B$33*Global_Assumptions!$B$31 | K11: =IF(D11>0,Global_Assumptions!$B$13+(I11+J11)/(D11*Global_Assumptions!$B$11),0) | L11: =Blend_Properties!$H$8*Global_Assumptions!$B$33*Global_Assumptions!$B$31 | M11: =IF(Blend_Properties!$G$8>0,(I11+J11)/Blend_Properties!$G$8,0) | N11: =Global_Assumptions!$B$33
A12: 10 | B12: =TEA_Hydraulics!$E$3 | C12: new | D12: =Blend_Properties!$F$8 | E12: =TEA_Hydraulics!D7 | F12: =(Global_Assumptions!$B$44*Global_Assumptions!$B$46*1000000)*TEA_Hydraulics!$E$3 | G12: =E12*Global_Assumptions!$B$39*1000000*(Blend_Properties!$F$8*Global_Assumptions!$B$38/8760/1000) | H12: =Global_Assumptions!$B$47*1000000+Blend_Properties!$F$8/365*Global_Assumptions!$B$49*Global_Assumptions!$B$48 | I12: =(F12+G12+H12)*Global_Assumptions!$B$5 | J12: =Blend_Properties!$F$8*Global_Assumptions!$B$38*Global_Assumptions!$B$19 + G12*Global_Assumptions!$B$41 + F12*Global_Assumptions!$B$50 + Global_Assumptions!$B$59*TEA_Hydraulics!$E$3 + Blend_Properties!$H$8*Global_Assumptions!$B$33*Global_Assumptions!$B$31 | K12: =IF(D12>0,Global_Assumptions!$B$13+(I12+J12)/(D12*Global_Assumptions!$B$11),0) | L12: =Blend_Properties!$H$8*Global_Assumptions!$B$33*Global_Assumptions!$B$31 | M12: =IF(Blend_Properties!$G$8>0,(I12+J12)/Blend_Properties!$G$8,0) | N12: =Global_Assumptions!$B$33
A13: 20 | B13: =TEA_Hydraulics!$B$3 | C13: retrofit | D13: =Blend_Properties!$F$9 | E13: =TEA_Hydraulics!C8 | F13: =(Global_Assumptions!$B$44*Global_Assumptions!$B$45*1000000)*TEA_Hydraulics!$B$3 | G13: 0 | H13: =Global_Assumptions!$B$47*1000000+Blend_Properties!$F$9/365*Global_Assumptions!$B$49*Global_Assumptions!$B$48 | I13: =(F13+G13+H13)*Global_Assumptions!$B$5 | J13: =Blend_Properties!$F$9*Global_Assumptions!$B$38*Global_Assumptions!$B$19 + G13*Global_Assumptions!$B$41 + F13*Global_Assumptions!$B$50 + Global_Assumptions!$B$58*TEA_Hydraulics!$B$3 + Blend_Properties!$H$9*Global_Assumptions!$B$33*Global_Assumptions!$B$31 | K13: =IF(D13>0,Global_Assumptions!$B$13+(I13+J13)/(D13*Global_Assumptions!$B$11),0) | L13: =Blend_Properties!$H$9*Global_Assumptions!$B$33*Global_Assumptions!$B$31 | M13: =IF(Blend_Properties!$G$9>0,(I13+J13)/Blend_Properties!$G$9,0) | N13: =Global_Assumptions!$B$33
A14: 20 | B14: =TEA_Hydraulics!$E$3 | C14: retrofit | D14: =Blend_Properties!$F$9 | E14: =TEA_Hydraulics!D8 | F14: =(Global_Assumptions!$B$44*Global_Assumptions!$B$45*1000000)*TEA_Hydraulics!$E$3 | G14: =E14*Global_Assumptions!$B$39*1000000*(Blend_Properties!$F$9*Global_Assumptions!$B$38/8760/1000) | H14: =Global_Assumptions!$B$47*1000000+Blend_Properties!$F$9/365*Global_Assumptions!$B$49*Global_Assumptions!$B$48 | I14: =(F14+G14+H14)*Global_Assumptions!$B$5 | J14: =Blend_Properties!$F$9*Global_Assumptions!$B$38*Global_Assumptions!$B$19 + G14*Global_Assumptions!$B$41 + F14*Global_Assumptions!$B$50 + Global_Assumptions!$B$58*TEA_Hydraulics!$E$3 + Blend_Properties!$H$9*Global_Assumptions!$B$33*Global_Assumptions!$B$31 | K14: =IF(D14>0,Global_Assumptions!$B$13+(I14+J14)/(D14*Global_Assumptions!$B$11),0) | L14: =Blend_Properties!$H$9*Global_Assumptions!$B$33*Global_Assumptions!$B$31 | M14: =IF(Blend_Properties!$G$9>0,(I14+J14)/Blend_Properties!$G$9,0) | N14: =Global_Assumptions!$B$33
A15: 20 | B15: =TEA_Hydraulics!$E$3 | C15: new | D15: =Blend_Properties!$F$9 | E15: =TEA_Hydraulics!D8 | F15: =(Global_Assumptions!$B$44*Global_Assumptions!$B$46*1000000)*TEA_Hydraulics!$E$3 | G15: =E15*Global_Assumptions!$B$39*1000000*(Blend_Properties!$F$9*Global_Assumptions!$B$38/8760/1000) | H15: =Global_Assumptions!$B$47*1000000+Blend_Properties!$F$9/365*Global_Assumptions!$B$49*Global_Assumptions!$B$48 | I15: =(F15+G15+H15)*Global_Assumptions!$B$5 | J15: =Blend_Properties!$F$9*Global_Assumptions!$B$38*Global_Assumptions!$B$19 + G15*Global_Assumptions!$B$41 + F15*Global_Assumptions!$B$50 + Global_Assumptions!$B$59*TEA_Hydraulics!$E$3 + Blend_Properties!$H$9*Global_Assumptions!$B$33*Global_Assumptions!$B$31 | K15: =IF(D15>0,Global_Assumptions!$B$13+(I15+J15)/(D15*Global_Assumptions!$B$11),0) | L15: =Blend_Properties!$H$9*Global_Assumptions!$B$33*Global_Assumptions!$B$31 | M15: =IF(Blend_Properties!$G$9>0,(I15+J15)/Blend_Properties!$G$9,0) | N15: =Global_Assumptions!$B$33
A16: 30 | B16: =TEA_Hydraulics!$B$3 | C16: retrofit | D16: =Blend_Properties!$F$10 | E16: =TEA_Hydraulics!C9 | F16: =(Global_Assumptions!$B$44*Global_Assumptions!$B$45*1000000)*TEA_Hydraulics!$B$3 | G16: 0 | H16: =Global_Assumptions!$B$47*1000000+Blend_Properties!$F$10/365*Global_Assumptions!$B$49*Global_Assumptions!$B$48 | I16: =(F16+G16+H16)*Global_Assumptions!$B$5 | J16: =Blend_Properties!$F$10*Global_Assumptions!$B$38*Global_Assumptions!$B$19 + G16*Global_Assumptions!$B$41 + F16*Global_Assumptions!$B$50 + Global_Assumptions!$B$58*TEA_Hydraulics!$B$3 + Blend_Properties!$H$10*Global_Assumptions!$B$33*Global_Assumptions!$B$31 | K16: =IF(D16>0,Global_Assumptions!$B$13+(I16+J16)/(D16*Global_Assumptions!$B$11),0) | L16: =Blend_Properties!$H$10*Global_Assumptions!$B$33*Global_Assumptions!$B$31 | M16: =IF(Blend_Properties!$G$10>0,(I16+J16)/Blend_Properties!$G$10,0) | N16: =Global_Assumptions!$B$33
A17: 30 | B17: =TEA_Hydraulics!$E$3 | C17: retrofit | D17: =Blend_Properties!$F$10 | E17: =TEA_Hydraulics!D9 | F17: =(Global_Assumptions!$B$44*Global_Assumptions!$B$45*1000000)*TEA_Hydraulics!$E$3 | G17: =E17*Global_Assumptions!$B$39*1000000*(Blend_Properties!$F$10*Global_Assumptions!$B$38/8760/1000) | H17: =Global_Assumptions!$B$47*1000000+Blend_Properties!$F$10/365*Global_Assumptions!$B$49*Global_Assumptions!$B$48 | I17: =(F17+G17+H17)*Global_Assumptions!$B$5 | J17: =Blend_Properties!$F$10*Global_Assumptions!$B$38*Global_Assumptions!$B$19 + G17*Global_Assumptions!$B$41 + F17*Global_Assumptions!$B$50 + Global_Assumptions!$B$58*TEA_Hydraulics!$E$3 + Blend_Properties!$H$10*Global_Assumptions!$B$33*Global_Assumptions!$B$31 | K17: =IF(D17>0,Global_Assumptions!$B$13+(I17+J17)/(D17*Global_Assumptions!$B$11),0) | L17: =Blend_Properties!$H$10*Global_Assumptions!$B$33*Global_Assumptions!$B$31 | M17: =IF(Blend_Properties!$G$10>0,(I17+J17)/Blend_Properties!$G$10,0) | N17: =Global_Assumptions!$B$33
A18: 30 | B18: =TEA_Hydraulics!$E$3 | C18: new | D18: =Blend_Properties!$F$10 | E18: =TEA_Hydraulics!D9 | F18: =(Global_Assumptions!$B$44*Global_Assumptions!$B$46*1000000)*TEA_Hydraulics!$E$3 | G18: =E18*Global_Assumptions!$B$39*1000000*(Blend_Properties!$F$10*Global_Assumptions!$B$38/8760/1000) | H18: =Global_Assumptions!$B$47*1000000+Blend_Properties!$F$10/365*Global_Assumptions!$B$49*Global_Assumptions!$B$48 | I18: =(F18+G18+H18)*Global_Assumptions!$B$5 | J18: =Blend_Properties!$F$10*Global_Assumptions!$B$38*Global_Assumptions!$B$19 + G18*Global_Assumptions!$B$41 + F18*Global_Assumptions!$B$50 + Global_Assumptions!$B$59*TEA_Hydraulics!$E$3 + Blend_Properties!$H$10*Global_Assumptions!$B$33*Global_Assumptions!$B$31 | K18: =IF(D18>0,Global_Assumptions!$B$13+(I18+J18)/(D18*Global_Assumptions!$B$11),0) | L18: =Blend_Properties!$H$10*Global_Assumptions!$B$33*Global_Assumptions!$B$31 | M18: =IF(Blend_Properties!$G$10>0,(I18+J18)/Blend_Properties!$G$10,0) | N18: =Global_Assumptions!$B$33
A19: 50 | B19: =TEA_Hydraulics!$B$3 | C19: retrofit | D19: =Blend_Properties!$F$11 | E19: =TEA_Hydraulics!C10 | F19: =(Global_Assumptions!$B$44*Global_Assumptions!$B$45*1000000)*TEA_Hydraulics!$B$3 | G19: 0 | H19: =Global_Assumptions!$B$47*1000000+Blend_Properties!$F$11/365*Global_Assumptions!$B$49*Global_Assumptions!$B$48 | I19: =(F19+G19+H19)*Global_Assumptions!$B$5 | J19: =Blend_Properties!$F$11*Global_Assumptions!$B$38*Global_Assumptions!$B$19 + G19*Global_Assumptions!$B$41 + F19*Global_Assumptions!$B$50 + Global_Assumptions!$B$58*TEA_Hydraulics!$B$3 + Blend_Properties!$H$11*Global_Assumptions!$B$33*Global_Assumptions!$B$31 | K19: =IF(D19>0,Global_Assumptions!$B$13+(I19+J19)/(D19*Global_Assumptions!$B$11),0) | L19: =Blend_Properties!$H$11*Global_Assumptions!$B$33*Global_Assumptions!$B$31 | M19: =IF(Blend_Properties!$G$11>0,(I19+J19)/Blend_Properties!$G$11,0) | N19: =Global_Assumptions!$B$33
A20: 50 | B20: =TEA_Hydraulics!$E$3 | C20: retrofit | D20: =Blend_Properties!$F$11 | E20: =TEA_Hydraulics!D10 | F20: =(Global_Assumptions!$B$44*Global_Assumptions!$B$45*1000000)*TEA_Hydraulics!$E$3 | G20: =E20*Global_Assumptions!$B$39*1000000*(Blend_Properties!$F$11*Global_Assumptions!$B$38/8760/1000) | H20: =Global_Assumptions!$B$47*1000000+Blend_Properties!$F$11/365*Global_Assumptions!$B$49*Global_Assumptions!$B$48 | I20: =(F20+G20+H20)*Global_Assumptions!$B$5 | J20: =Blend_Properties!$F$11*Global_Assumptions!$B$38*Global_Assumptions!$B$19 + G20*Global_Assumptions!$B$41 + F20*Global_Assumptions!$B$50 + Global_Assumptions!$B$58*TEA_Hydraulics!$E$3 + Blend_Properties!$H$11*Global_Assumptions!$B$33*Global_Assumptions!$B$31 | K20: =IF(D20>0,Global_Assumptions!$B$13+(I20+J20)/(D20*Global_Assumptions!$B$11),0) | L20: =Blend_Properties!$H$11*Global_Assumptions!$B$33*Global_Assumptions!$B$31 | M20: =IF(Blend_Properties!$G$11>0,(I20+J20)/Blend_Properties!$G$11,0) | N20: =Global_Assumptions!$B$33
A21: 50 | B21: =TEA_Hydraulics!$E$3 | C21: new | D21: =Blend_Properties!$F$11 | E21: =TEA_Hydraulics!D10 | F21: =(Global_Assumptions!$B$44*Global_Assumptions!$B$46*1000000)*TEA_Hydraulics!$E$3 | G21: =E21*Global_Assumptions!$B$39*1000000*(Blend_Properties!$F$11*Global_Assumptions!$B$38/8760/1000) | H21: =Global_Assumptions!$B$47*1000000+Blend_Properties!$F$11/365*Global_Assumptions!$B$49*Global_Assumptions!$B$48 | I21: =(F21+G21+H21)*Global_Assumptions!$B$5 | J21: =Blend_Properties!$F$11*Global_Assumptions!$B$38*Global_Assumptions!$B$19 + G21*Global_Assumptions!$B$41 + F21*Global_Assumptions!$B$50 + Global_Assumptions!$B$59*TEA_Hydraulics!$E$3 + Blend_Properties!$H$11*Global_Assumptions!$B$33*Global_Assumptions!$B$31 | K21: =IF(D21>0,Global_Assumptions!$B$13+(I21+J21)/(D21*Global_Assumptions!$B$11),0) | L21: =Blend_Properties!$H$11*Global_Assumptions!$B$33*Global_Assumptions!$B$31 | M21: =IF(Blend_Properties!$G$11>0,(I21+J21)/Blend_Properties!$G$11,0) | N21: =Global_Assumptions!$B$33
A22: 75 | B22: =TEA_Hydraulics!$B$3 | C22: retrofit | D22: =Blend_Properties!$F$12 | E22: =TEA_Hydraulics!C11 | F22: =(Global_Assumptions!$B$44*Global_Assumptions!$B$45*1000000)*TEA_Hydraulics!$B$3 | G22: 0 | H22: =Global_Assumptions!$B$47*1000000+Blend_Properties!$F$12/365*Global_Assumptions!$B$49*Global_Assumptions!$B$48 | I22: =(F22+G22+H22)*Global_Assumptions!$B$5 | J22: =Blend_Properties!$F$12*Global_Assumptions!$B$38*Global_Assumptions!$B$19 + G22*Global_Assumptions!$B$41 + F22*Global_Assumptions!$B$50 + Global_Assumptions!$B$58*TEA_Hydraulics!$B$3 + Blend_Properties!$H$12*Global_Assumptions!$B$33*Global_Assumptions!$B$31 | K22: =IF(D22>0,Global_Assumptions!$B$13+(I22+J22)/(D22*Global_Assumptions!$B$11),0) | L22: =Blend_Properties!$H$12*Global_Assumptions!$B$33*Global_Assumptions!$B$31 | M22: =IF(Blend_Properties!$G$12>0,(I22+J22)/Blend_Properties!$G$12,0) | N22: =Global_Assumptions!$B$33
A23: 75 | B23: =TEA_Hydraulics!$E$3 | C23: retrofit | D23: =Blend_Properties!$F$12 | E23: =TEA_Hydraulics!D11 | F23: =(Global_Assumptions!$B$44*Global_Assumptions!$B$45*1000000)*TEA_Hydraulics!$E$3 | G23: =E23*Global_Assumptions!$B$39*1000000*(Blend_Properties!$F$12*Global_Assumptions!$B$38/8760/1000) | H23: =Global_Assumptions!$B$47*1000000+Blend_Properties!$F$12/365*Global_Assumptions!$B$49*Global_Assumptions!$B$48 | I23: =(F23+G23+H23)*Global_Assumptions!$B$5 | J23: =Blend_Properties!$F$12*Global_Assumptions!$B$38*Global_Assumptions!$B$19 + G23*Global_Assumptions!$B$41 + F23*Global_Assumptions!$B$50 + Global_Assumptions!$B$58*TEA_Hydraulics!$E$3 + Blend_Properties!$H$12*Global_Assumptions!$B$33*Global_Assumptions!$B$31 | K23: =IF(D23>0,Global_Assumptions!$B$13+(I23+J23)/(D23*Global_Assumptions!$B$11),0) | L23: =Blend_Properties!$H$12*Global_Assumptions!$B$33*Global_Assumptions!$B$31 | M23: =IF(Blend_Properties!$G$12>0,(I23+J23)/Blend_Properties!$G$12,0) | N23: =Global_Assumptions!$B$33
A24: 75 | B24: =TEA_Hydraulics!$E$3 | C24: new | D24: =Blend_Properties!$F$12 | E24: =TEA_Hydraulics!D11 | F24: =(Global_Assumptions!$B$44*Global_Assumptions!$B$46*1000000)*TEA_Hydraulics!$E$3 | G24: =E24*Global_Assumptions!$B$39*1000000*(Blend_Properties!$F$12*Global_Assumptions!$B$38/8760/1000) | H24: =Global_Assumptions!$B$47*1000000+Blend_Properties!$F$12/365*Global_Assumptions!$B$49*Global_Assumptions!$B$48 | I24: =(F24+G24+H24)*Global_Assumptions!$B$5 | J24: =Blend_Properties!$F$12*Global_Assumptions!$B$38*Global_Assumptions!$B$19 + G24*Global_Assumptions!$B$41 + F24*Global_Assumptions!$B$50 + Global_Assumptions!$B$59*TEA_Hydraulics!$E$3 + Blend_Properties!$H$12*Global_Assumptions!$B$33*Global_Assumptions!$B$31 | K24: =IF(D24>0,Global_Assumptions!$B$13+(I24+J24)/(D24*Global_Assumptions!$B$11),0) | L24: =Blend_Properties!$H$12*Global_Assumptions!$B$33*Global_Assumptions!$B$31 | M24: =IF(Blend_Properties!$G$12>0,(I24+J24)/Blend_Properties!$G$12,0) | N24: =Global_Assumptions!$B$33
A25: 100 | B25: =TEA_Hydraulics!$B$3 | C25: retrofit | D25: =Blend_Properties!$F$13 | E25: =TEA_Hydraulics!C12 | F25: =(Global_Assumptions!$B$44*Global_Assumptions!$B$45*1000000)*TEA_Hydraulics!$B$3 | G25: 0 | H25: =Global_Assumptions!$B$47*1000000+Blend_Properties!$F$13/365*Global_Assumptions!$B$49*Global_Assumptions!$B$48 | I25: =(F25+G25+H25)*Global_Assumptions!$B$5 | J25: =Blend_Properties!$F$13*Global_Assumptions!$B$38*Global_Assumptions!$B$19 + G25*Global_Assumptions!$B$41 + F25*Global_Assumptions!$B$50 + Global_Assumptions!$B$58*TEA_Hydraulics!$B$3 + Blend_Properties!$H$13*Global_Assumptions!$B$33*Global_Assumptions!$B$31 | K25: =IF(D25>0,Global_Assumptions!$B$13+(I25+J25)/(D25*Global_Assumptions!$B$11),0) | L25: =Blend_Properties!$H$13*Global_Assumptions!$B$33*Global_Assumptions!$B$31 | M25: =IF(Blend_Properties!$G$13>0,(I25+J25)/Blend_Properties!$G$13,0) | N25: =Global_Assumptions!$B$33
A26: 100 | B26: =TEA_Hydraulics!$E$3 | C26: retrofit | D26: =Blend_Properties!$F$13 | E26: =TEA_Hydraulics!D12 | F26: =(Global_Assumptions!$B$44*Global_Assumptions!$B$45*1000000)*TEA_Hydraulics!$E$3 | G26: =E26*Global_Assumptions!$B$39*1000000*(Blend_Properties!$F$13*Global_Assumptions!$B$38/8760/1000) | H26: =Global_Assumptions!$B$47*1000000+Blend_Properties!$F$13/365*Global_Assumptions!$B$49*Global_Assumptions!$B$48 | I26: =(F26+G26+H26)*Global_Assumptions!$B$5 | J26: =Blend_Properties!$F$13*Global_Assumptions!$B$38*Global_Assumptions!$B$19 + G26*Global_Assumptions!$B$41 + F26*Global_Assumptions!$B$50 + Global_Assumptions!$B$58*TEA_Hydraulics!$E$3 + Blend_Properties!$H$13*Global_Assumptions!$B$33*Global_Assumptions!$B$31 | K26: =IF(D26>0,Global_Assumptions!$B$13+(I26+J26)/(D26*Global_Assumptions!$B$11),0) | L26: =Blend_Properties!$H$13*Global_Assumptions!$B$33*Global_Assumptions!$B$31 | M26: =IF(Blend_Properties!$G$13>0,(I26+J26)/Blend_Properties!$G$13,0) | N26: =Global_Assumptions!$B$33
A27: 100 | B27: =TEA_Hydraulics!$E$3 | C27: new | D27: =Blend_Properties!$F$13 | E27: =TEA_Hydraulics!D12 | F27: =(Global_Assumptions!$B$44*Global_Assumptions!$B$46*1000000)*TEA_Hydraulics!$E$3 | G27: =E27*Global_Assumptions!$B$39*1000000*(Blend_Properties!$F$13*Global_Assumptions!$B$38/8760/1000) | H27: =Global_Assumptions!$B$47*1000000+Blend_Properties!$F$13/365*Global_Assumptions!$B$49*Global_Assumptions!$B$48 | I27: =(F27+G27+H27)*Global_Assumptions!$B$5 | J27: =Blend_Properties!$F$13*Global_Assumptions!$B$38*Global_Assumptions!$B$19 + G27*Global_Assumptions!$B$41 + F27*Global_Assumptions!$B$50 + Global_Assumptions!$B$59*TEA_Hydraulics!$E$3 + Blend_Properties!$H$13*Global_Assumptions!$B$33*Global_Assumptions!$B$31 | K27: =IF(D27>0,Global_Assumptions!$B$13+(I27+J27)/(D27*Global_Assumptions!$B$11),0) | L27: =Blend_Properties!$H$13*Global_Assumptions!$B$33*Global_Assumptions!$B$31 | M27: =IF(Blend_Properties!$G$13>0,(I27+J27)/Blend_Properties!$G$13,0) | N27: =Global_Assumptions!$B$33

Sheet Lifecycle_50yr
A1: 50-YEAR LIFECYCLE & DERIVED AVAILABILITY — UCI Microturbine
A2: PoF rises with age and resets at condition-based maintenance (when an inspection finds PoF>threshold). Availability is DERIVED from inspection + maintenance + expected-failure downtime over the 50-yr horizon (not an input).
A3: Class | B3: Count | C3: Insp int (yr) | D3: Thr | E3: MTTR (h) | F3: Insp down (h) | G3: Insp $/event | H3: Maint $/event | I3: PoF20 H2 | J3: lambda (/hr) | K3: MTTF (yr) | L3: Tau_thr (yr) | M3: Maint int M (yr) | N3: #Insp 50yr | O3: #Maint 50yr | P3: Failure h/yr | Q3: Downtime 50yr (h) | R3: Gen | S3: CO2 | T3: (1-PoF)^n
A4: pipe | B4: 1 | C4: 7 | D4: 0.3 | E4: 240 | F4: 24 | G4: 33450 | H4: 150000 | I4: =PoF_Summary!E4 | J4: =-LN(1-MIN(0.99,I4))/(8760*Global_Assumptions!$B$52) | K4: =1/(J4*8760) | L4: =-LN(1-D4)/(J4*8760) | M4: =C4*CEILING(L4/C4,1) | N4: =INT(Global_Assumptions!$B$63/C4) | O4: =INT(Global_Assumptions!$B$63/M4) | P4: =(1-EXP(-J4*8760))*E4 | Q4: =B4*(N4*F4+O4*E4+Global_Assumptions!$B$63*P4) | R4: 0 | S4: 0 | T4: =(1-I4)^B4
A5: valve | B5: 3 | C5: 2 | D5: 0.3 | E5: 24 | F5: 4 | G5: 1500 | H5: 8000 | I5: =PoF_Summary!E5 | J5: =-LN(1-MIN(0.99,I5))/(8760*Global_Assumptions!$B$52) | K5: =1/(J5*8760) | L5: =-LN(1-D5)/(J5*8760) | M5: =C5*CEILING(L5/C5,1) | N5: =INT(Global_Assumptions!$B$63/C5) | O5: =INT(Global_Assumptions!$B$63/M5) | P5: =(1-EXP(-J5*8760))*E5 | Q5: =B5*(N5*F5+O5*E5+Global_Assumptions!$B$63*P5) | R5: 0 | S5: 0 | T5: =(1-I5)^B5
A6: regulator | B6: 1 | C6: 3 | D6: 0.3 | E6: 16 | F6: 3 | G6: 1200 | H6: 6000 | I6: =PoF_Summary!E6 | J6: =-LN(1-MIN(0.99,I6))/(8760*Global_Assumptions!$B$52) | K6: =1/(J6*8760) | L6: =-LN(1-D6)/(J6*8760) | M6: =C6*CEILING(L6/C6,1) | N6: =INT(Global_Assumptions!$B$63/C6) | O6: =INT(Global_Assumptions!$B$63/M6) | P6: =(1-EXP(-J6*8760))*E6 | Q6: =B6*(N6*F6+O6*E6+Global_Assumptions!$B$63*P6) | R6: 0 | S6: 0 | T6: =(1-I6)^B6
A7: meter | B7: 1 | C7: 2 | D7: 0.3 | E7: 8 | F7: 2 | G7: 800 | H7: 4000 | I7: =PoF_Summary!E7 | J7: =-LN(1-MIN(0.99,I7))/(8760*Global_Assumptions!$B$52) | K7: =1/(J7*8760) | L7: =-LN(1-D7)/(J7*8760) | M7: =C7*CEILING(L7/C7,1) | N7: =INT(Global_Assumptions!$B$63/C7) | O7: =INT(Global_Assumptions!$B$63/M7) | P7: =(1-EXP(-J7*8760))*E7 | Q7: =B7*(N7*F7+O7*E7+Global_Assumptions!$B$63*P7) | R7: 0 | S7: 0 | T7: =(1-I7)^B7
A8: storage | B8: 1 | C8: 5 | D8: 0.3 | E8: 48 | F8: 8 | G8: 4000 | H8: 12000 | I8: =PoF_Summary!E8 | J8: =-LN(1-MIN(0.99,I8))/(8760*Global_Assumptions!$B$52) | K8: =1/(J8*8760) | L8: =-LN(1-D8)/(J8*8760) | M8: =C8*CEILING(L8/C8,1) | N8: =INT(Global_Assumptions!$B$63/C8) | O8: =INT(Global_Assumptions!$B$63/M8) | P8: =(1-EXP(-J8*8760))*E8 | Q8: =B8*(N8*F8+O8*E8+Global_Assumptions!$B$63*P8) | R8: 0 | S8: 0 | T8: =(1-I8)^B8
A9: microturbine | B9: 1 | C9: 1 | D9: 0.25 | E9: 120 | F9: 24 | G9: 8000 | H9: 45000 | I9: =PoF_Summary!E9 | J9: =-LN(1-MIN(0.99,I9))/(8760*Global_Assumptions!$B$52) | K9: =1/(J9*8760) | L9: =-LN(1-D9)/(J9*8760) | M9: =C9*CEILING(L9/C9,1) | N9: =INT(Global_Assumptions!$B$63/C9) | O9: =INT(Global_Assumptions!$B$63/M9) | P9: =(1-EXP(-J9*8760))*E9 | Q9: =B9*(N9*F9+O9*E9+Global_Assumptions!$B$63*P9) | R9: 1 | S9: 1 | T9: =(1-I9)^B9
A10: heat_exchanger | B10: 1 | C10: 3 | D10: 0.3 | E10: 120 | F10: 24 | G10: 9000 | H10: 35000 | I10: =PoF_Summary!E10 | J10: =-LN(1-MIN(0.99,I10))/(8760*Global_Assumptions!$B$52) | K10: =1/(J10*8760) | L10: =-LN(1-D10)/(J10*8760) | M10: =C10*CEILING(L10/C10,1) | N10: =INT(Global_Assumptions!$B$63/C10) | O10: =INT(Global_Assumptions!$B$63/M10) | P10: =(1-EXP(-J10*8760))*E10 | Q10: =B10*(N10*F10+O10*E10+Global_Assumptions!$B$63*P10) | R10: 0 | S10: 0 | T10: =(1-I10)^B10
A12: SYSTEM ROLL-UP (derived from the table above)
A13: Total downtime over 50 yr (h) | B13: =SUM(Q4:Q10)
A14: Average annual downtime (h) | B14: =B13/Global_Assumptions!$B$63
A15: DERIVED AVAILABILITY (50-yr mean) | B15: =1-MIN(8760,B14)/8760
A16: System PoF20 (series) | B16: =1-PRODUCT(T4:T10)
A17: System MTTF (series, yr) | B17: =1/(SUMPRODUCT(B4:B10,J4:J10)*8760)
A18: Avg inspection cost ($/yr) | B18: =SUMPRODUCT(B4:B10,G4:G10,N4:N10)/Global_Assumptions!$B$63
A19: Avg maintenance cost ($/yr) | B19: =SUMPRODUCT(B4:B10,H4:H10,O4:O10)/Global_Assumptions!$B$63
A21: #Maint over 50 yr is 0 where the component's PoF never reaches the maintenance threshold within the horizon (M > 50).

Sheet Fuel_Cost
A1: BLENDED FUEL COST — UCI Microturbine
A2: Fuel = (NG portion + H2 portion)/combustion-efficiency. THERMOFLEX-VALIDATED: LHV efficiency RISES slightly with H2 (Sol Titan +1.0%, C65/C200 +0.19%), so eff=1+gain*(blend/100) — the earlier 3% derate is rejected. Gross (availability applied in Cashflow_50yr).
A3: Blend % | B3: H2 energy frac | C3: Comb. eff. | D3: Fuel NG ($/yr) | E3: H2 production ($/yr) | F3: Total fuel ($/yr)
A4: 0 | B4: =Blend_Properties!$B$6 | C4: =1+Global_Assumptions!$B$64*(A4/100) | D4: =Blend_Properties!$B$3*(1-B4)*Global_Assumptions!$B$16 | E4: =Blend_Properties!$F$6*Global_Assumptions!$B$13 | F4: =(D4+E4)/C4
A5: 5 | B5: =Blend_Properties!$B$7 | C5: =1+Global_Assumptions!$B$64*(A5/100) | D5: =Blend_Properties!$B$3*(1-B5)*Global_Assumptions!$B$16 | E5: =Blend_Properties!$F$7*Global_Assumptions!$B$13 | F5: =(D5+E5)/C5
A6: 10 | B6: =Blend_Properties!$B$8 | C6: =1+Global_Assumptions!$B$64*(A6/100) | D6: =Blend_Properties!$B$3*(1-B6)*Global_Assumptions!$B$16 | E6: =Blend_Properties!$F$8*Global_Assumptions!$B$13 | F6: =(D6+E6)/C6
A7: 20 | B7: =Blend_Properties!$B$9 | C7: =1+Global_Assumptions!$B$64*(A7/100) | D7: =Blend_Properties!$B$3*(1-B7)*Global_Assumptions!$B$16 | E7: =Blend_Properties!$F$9*Global_Assumptions!$B$13 | F7: =(D7+E7)/C7
A8: 30 | B8: =Blend_Properties!$B$10 | C8: =1+Global_Assumptions!$B$64*(A8/100) | D8: =Blend_Properties!$B$3*(1-B8)*Global_Assumptions!$B$16 | E8: =Blend_Properties!$F$10*Global_Assumptions!$B$13 | F8: =(D8+E8)/C8
A9: 50 | B9: =Blend_Properties!$B$11 | C9: =1+Global_Assumptions!$B$64*(A9/100) | D9: =Blend_Properties!$B$3*(1-B9)*Global_Assumptions!$B$16 | E9: =Blend_Properties!$F$11*Global_Assumptions!$B$13 | F9: =(D9+E9)/C9
A10: 75 | B10: =Blend_Properties!$B$12 | C10: =1+Global_Assumptions!$B$64*(A10/100) | D10: =Blend_Properties!$B$3*(1-B10)*Global_Assumptions!$B$16 | E10: =Blend_Properties!$F$12*Global_Assumptions!$B$13 | F10: =(D10+E10)/C10
A11: 100 | B11: =Blend_Properties!$B$13 | C11: =1+Global_Assumptions!$B$64*(A11/100) | D11: =Blend_Properties!$B$3*(1-B11)*Global_Assumptions!$B$16 | E11: =Blend_Properties!$F$13*Global_Assumptions!$B$13 | F11: =(D11+E11)/C11

Sheet Thermoflex_Validation
A1: THERMOFLEX THERMODYNAMIC VALIDATION & FUEL-SYSTEM CONSTRAINTS
A2: GT PRO/Thermoflex simulation of the UCI turbines (Sol Titan 130, Capstone C65/C200) over 0->100% H2. Validates the model's thermodynamic assumptions and sets fuel-system hardware constraints.
A4: A. Validated thermodynamic relationships
A5: Quantity | B5: NG (0%) | C5: 50% H2 | D5: 100% H2 | E5: Trend | G5: Source & formula
A6: Fuel volumetric flow (÷NG) | B6: 1.00x | C6: 1.54x | D6: 3.39x | E6: RISES | G6: Thermoflex fit VF=1/((1-v)+0.295v)
A7: Fuel mass flow | B7: 1.00x | C7: ~0.79x | D7: ~0.38x | E7: falls | G7: H2 has lower mass per unit energy
A8: Gross LHV efficiency (turbine) | B8: 33.05% | C8: ~33.4% | D8: 33.88% | E8: +1.0% | G8: Thermoflex Sol Titan 130
A9: Gross LHV efficiency (microturbine) | B9: 41.68% | C9: ~41.70% | D9: 41.76% | E9: +0.19% | G9: Thermoflex C65/C200
A10: Exhaust CO2 mol% | B10: 1.86% | C10: 1.39% | D10: 0.000% | E10: falls to ~0 | G10: CO2=1.861*(1-Efrac)
A11: Sol Titan gross power | B11: 13.29 MW | C11: ~13.5 MW | D11: 13.88 MW | E11: RISES | G11: constant TIT 1422K
A12: Turbine outlet temp (TOT) | B12: 768.3 K | C12: ~766 K | D12: 764.2 K | E12: falls <10K | G12: within limit
A14: B. Fuel-system hard constraints (Thermoflex + UCI operator-confirmed)
A15: Constraint | B15: Trigger | C15: Threshold | D15: Replacement CAPEX | G15: Basis
A16: Larger fuel metering valve | B16: Fuel volumetric flow > installed Cv margin | C16: ~28% H2 (25% margin) | D16: $25,000 | G16: Thermoflex: fuel vol flow 3.39x at 100% H2; operator-confirmed larger valve needed
A17: High-flame-speed injectors | B17: Blend above flashback threshold | C17: 30% H2 | D17: $80,000 | G17: Operator-confirmed: high blends need special high-flame-speed injectors (H2 flame speed ~8x NG)
A19: Note: efficiency values applied harmonized at +1.0%/100% in Global_Assumptions B64; microturbine actual +0.19% (sub-1% fuel-cost effect). CAPEX are screening placeholders pending OEM quotation.

Sheet Cashflow_50yr
A1: DETAILED 50-YEAR CASHFLOW — UCI Microturbine (selectable scenario)
A2: Change the blue controls to switch scenario. Capital is taken in year 1; inspection & maintenance follow the lifecycle schedule; fuel, revenue and credits scale with the derived per-year availability. Discounted at the utility rate over 50 years.
A3: Scenario (1=near-retrofit, 2=far-retrofit, 3=far-new) | B3: 1 | D3: H2 demand (kg/yr) | E3: =INDEX(Blend_Properties!$F$6:$F$13,B8) | G3: Comp CAPEX ($) | H3: =SUMIFS(Scenario_Results!$G$4:$G$27,Scenario_Results!$A$4:$A$27,$B$4,Scenario_Results!$B$4:$B$27,$B$7,Scenario_Results!$C$4:$C$27,$B$6)
A4: Blend % (vol) | B4: 20 | D4: H2 energy fraction | E4: =INDEX(Blend_Properties!$B$6:$B$13,B8) | G4: Skid+storage ($) | H4: =SUMIFS(Scenario_Results!$H$4:$H$27,Scenario_Results!$A$4:$A$27,$B$4,Scenario_Results!$B$4:$B$27,$B$7,Scenario_Results!$C$4:$C$27,$B$6)
A5: Injection | B5: =IF(B3=1,"near","far") | D5: CO2 avoided (t/yr) | E5: =INDEX(Blend_Properties!$G$6:$G$13,B8) | G5: Compressors | H5: =SUMIFS(Scenario_Results!$E$4:$E$27,Scenario_Results!$A$4:$A$27,$B$4,Scenario_Results!$B$4:$B$27,$B$7,Scenario_Results!$C$4:$C$27,$B$6)
A6: Pathway | B6: =IF(B3=3,"new","retrofit") | D6: Delivered energy (GJ/yr) | E6: =Blend_Properties!$B$3*((1-B4/100)+(B4/100)*Global_Assumptions!$B$26) | G6: Total CAPEX ($) | H6: =E8+H3+H4
A7: Selected distance (mi) | B7: =IF(B3=1,TEA_Hydraulics!$B$3,TEA_Hydraulics!$E$3) | D7: Combustion efficiency | E7: =1+Global_Assumptions!$B$64*(B4/100) | G7: Storage CAPEX ($) | H7: =E3/365*Global_Assumptions!$B$49*Global_Assumptions!$B$48
A8: Blend index | B8: =MATCH(B4,Blend_Properties!$A$6:$A$13,0) | D8: Pipe CAPEX ($) | E8: =SUMIFS(Scenario_Results!$F$4:$F$27,Scenario_Results!$A$4:$A$27,$B$4,Scenario_Results!$B$4:$B$27,$B$7,Scenario_Results!$C$4:$C$27,$B$6) | G8: Pressure adder ($/kg) | H8: 0.15
A10: Annual O&M constants
A11: Compression elec ($/yr) | B11: =E3*Global_Assumptions!$B$38*Global_Assumptions!$B$19
A12: Compressor maint ($/yr) | B12: =H3*Global_Assumptions!$B$41
A13: Pipe O&M ($/yr) | B13: =E8*Global_Assumptions!$B$50
A14: Pressure O&M ($/yr) | B14: =H8*E3
A15: Storage O&M ($/yr) | B15: =H7*Global_Assumptions!$B$65
A17: Year | B17: Avail. | C17: CAPEX ($) | D17: Inspect ($) | E17: Maint ($) | F17: Fuel NG ($) | G17: H2 prod ($) | H17: Stor O&M ($) | I17: O&M/Compr ($) | J17: Revenue ($) | K17: Carbon cr ($) | L17: Net ($) | M17: Disc. net ($)
A18: 1 | B18: =1-MIN(8760,SUMPRODUCT(Lifecycle_50yr!$B$4:$B$10,Lifecycle_50yr!$F$4:$F$10,--(MOD($A18,Lifecycle_50yr!$C$4:$C$10)=0))+SUMPRODUCT(Lifecycle_50yr!$B$4:$B$10,Lifecycle_50yr!$E$4:$E$10,--(MOD($A18,Lifecycle_50yr!$M$4:$M$10)=0))+SUMPRODUCT(Lifecycle_50yr!$B$4:$B$10,Lifecycle_50yr!$P$4:$P$10))/8760 | C18: =IF($A18=1,$H$6,0) | D18: =SUMPRODUCT(Lifecycle_50yr!$B$4:$B$10,Lifecycle_50yr!$G$4:$G$10,--(MOD($A18,Lifecycle_50yr!$C$4:$C$10)=0)) | E18: =SUMPRODUCT(Lifecycle_50yr!$B$4:$B$10,Lifecycle_50yr!$H$4:$H$10,--(MOD($A18,Lifecycle_50yr!$M$4:$M$10)=0)) | F18: =Blend_Properties!$B$3*(1-$E$4)*Global_Assumptions!$B$16/$E$7*B18 | G18: =$E$3*Global_Assumptions!$B$13/$E$7*B18 | H18: =$B$15*B18 | I18: =($B$11+$B$14)*B18+$B$12+$B$13 | J18: =$E$3*Global_Assumptions!$B$66*B18 | K18: =($E$5*Global_Assumptions!$B$20+$E$3*Global_Assumptions!$B$68*(--($A18<=Global_Assumptions!$B$86)))*B18 | L18: =J18+K18-(C18+D18+E18+F18+G18+H18+I18) | M18: =L18/(1+Global_Assumptions!$B$7)^$A18
A19: 2 | B19: =1-MIN(8760,SUMPRODUCT(Lifecycle_50yr!$B$4:$B$10,Lifecycle_50yr!$F$4:$F$10,--(MOD($A19,Lifecycle_50yr!$C$4:$C$10)=0))+SUMPRODUCT(Lifecycle_50yr!$B$4:$B$10,Lifecycle_50yr!$E$4:$E$10,--(MOD($A19,Lifecycle_50yr!$M$4:$M$10)=0))+SUMPRODUCT(Lifecycle_50yr!$B$4:$B$10,Lifecycle_50yr!$P$4:$P$10))/8760 | C19: =IF($A19=1,$H$6,0) | D19: =SUMPRODUCT(Lifecycle_50yr!$B$4:$B$10,Lifecycle_50yr!$G$4:$G$10,--(MOD($A19,Lifecycle_50yr!$C$4:$C$10)=0)) | E19: =SUMPRODUCT(Lifecycle_50yr!$B$4:$B$10,Lifecycle_50yr!$H$4:$H$10,--(MOD($A19,Lifecycle_50yr!$M$4:$M$10)=0)) | F19: =Blend_Properties!$B$3*(1-$E$4)*Global_Assumptions!$B$16/$E$7*B19 | G19: =$E$3*Global_Assumptions!$B$13/$E$7*B19 | H19: =$B$15*B19 | I19: =($B$11+$B$14)*B19+$B$12+$B$13 | J19: =$E$3*Global_Assumptions!$B$66*B19 | K19: =($E$5*Global_Assumptions!$B$20+$E$3*Global_Assumptions!$B$68*(--($A19<=Global_Assumptions!$B$86)))*B19 | L19: =J19+K19-(C19+D19+E19+F19+G19+H19+I19) | M19: =L19/(1+Global_Assumptions!$B$7)^$A19
A20: 3 | B20: =1-MIN(8760,SUMPRODUCT(Lifecycle_50yr!$B$4:$B$10,Lifecycle_50yr!$F$4:$F$10,--(MOD($A20,Lifecycle_50yr!$C$4:$C$10)=0))+SUMPRODUCT(Lifecycle_50yr!$B$4:$B$10,Lifecycle_50yr!$E$4:$E$10,--(MOD($A20,Lifecycle_50yr!$M$4:$M$10)=0))+SUMPRODUCT(Lifecycle_50yr!$B$4:$B$10,Lifecycle_50yr!$P$4:$P$10))/8760 | C20: =IF($A20=1,$H$6,0) | D20: =SUMPRODUCT(Lifecycle_50yr!$B$4:$B$10,Lifecycle_50yr!$G$4:$G$10,--(MOD($A20,Lifecycle_50yr!$C$4:$C$10)=0)) | E20: =SUMPRODUCT(Lifecycle_50yr!$B$4:$B$10,Lifecycle_50yr!$H$4:$H$10,--(MOD($A20,Lifecycle_50yr!$M$4:$M$10)=0)) | F20: =Blend_Properties!$B$3*(1-$E$4)*Global_Assumptions!$B$16/$E$7*B20 | G20: =$E$3*Global_Assumptions!$B$13/$E$7*B20 | H20: =$B$15*B20 | I20: =($B$11+$B$14)*B20+$B$12+$B$13 | J20: =$E$3*Global_Assumptions!$B$66*B20 | K20: =($E$5*Global_Assumptions!$B$20+$E$3*Global_Assumptions!$B$68*(--($A20<=Global_Assumptions!$B$86)))*B20 | L20: =J20+K20-(C20+D20+E20+F20+G20+H20+I20) | M20: =L20/(1+Global_Assumptions!$B$7)^$A20
A21: 4 | B21: =1-MIN(8760,SUMPRODUCT(Lifecycle_50yr!$B$4:$B$10,Lifecycle_50yr!$F$4:$F$10,--(MOD($A21,Lifecycle_50yr!$C$4:$C$10)=0))+SUMPRODUCT(Lifecycle_50yr!$B$4:$B$10,Lifecycle_50yr!$E$4:$E$10,--(MOD($A21,Lifecycle_50yr!$M$4:$M$10)=0))+SUMPRODUCT(Lifecycle_50yr!$B$4:$B$10,Lifecycle_50yr!$P$4:$P$10))/8760 | C21: =IF($A21=1,$H$6,0) | D21: =SUMPRODUCT(Lifecycle_50yr!$B$4:$B$10,Lifecycle_50yr!$G$4:$G$10,--(MOD($A21,Lifecycle_50yr!$C$4:$C$10)=0)) | E21: =SUMPRODUCT(Lifecycle_50yr!$B$4:$B$10,Lifecycle_50yr!$H$4:$H$10,--(MOD($A21,Lifecycle_50yr!$M$4:$M$10)=0)) | F21: =Blend_Properties!$B$3*(1-$E$4)*Global_Assumptions!$B$16/$E$7*B21 | G21: =$E$3*Global_Assumptions!$B$13/$E$7*B21 | H21: =$B$15*B21 | I21: =($B$11+$B$14)*B21+$B$12+$B$13 | J21: =$E$3*Global_Assumptions!$B$66*B21 | K21: =($E$5*Global_Assumptions!$B$20+$E$3*Global_Assumptions!$B$68*(--($A21<=Global_Assumptions!$B$86)))*B21 | L21: =J21+K21-(C21+D21+E21+F21+G21+H21+I21) | M21: =L21/(1+Global_Assumptions!$B$7)^$A21
A22: 5 | B22: =1-MIN(8760,SUMPRODUCT(Lifecycle_50yr!$B$4:$B$10,Lifecycle_50yr!$F$4:$F$10,--(MOD($A22,Lifecycle_50yr!$C$4:$C$10)=0))+SUMPRODUCT(Lifecycle_50yr!$B$4:$B$10,Lifecycle_50yr!$E$4:$E$10,--(MOD($A22,Lifecycle_50yr!$M$4:$M$10)=0))+SUMPRODUCT(Lifecycle_50yr!$B$4:$B$10,Lifecycle_50yr!$P$4:$P$10))/8760 | C22: =IF($A22=1,$H$6,0) | D22: =SUMPRODUCT(Lifecycle_50yr!$B$4:$B$10,Lifecycle_50yr!$G$4:$G$10,--(MOD($A22,Lifecycle_50yr!$C$4:$C$10)=0)) | E22: =SUMPRODUCT(Lifecycle_50yr!$B$4:$B$10,Lifecycle_50yr!$H$4:$H$10,--(MOD($A22,Lifecycle_50yr!$M$4:$M$10)=0)) | F22: =Blend_Properties!$B$3*(1-$E$4)*Global_Assumptions!$B$16/$E$7*B22 | G22: =$E$3*Global_Assumptions!$B$13/$E$7*B22 | H22: =$B$15*B22 | I22: =($B$11+$B$14)*B22+$B$12+$B$13 | J22: =$E$3*Global_Assumptions!$B$66*B22 | K22: =($E$5*Global_Assumptions!$B$20+$E$3*Global_Assumptions!$B$68*(--($A22<=Global_Assumptions!$B$86)))*B22 | L22: =J22+K22-(C22+D22+E22+F22+G22+H22+I22) | M22: =L22/(1+Global_Assumptions!$B$7)^$A22
A23: 6 | B23: =1-MIN(8760,SUMPRODUCT(Lifecycle_50yr!$B$4:$B$10,Lifecycle_50yr!$F$4:$F$10,--(MOD($A23,Lifecycle_50yr!$C$4:$C$10)=0))+SUMPRODUCT(Lifecycle_50yr!$B$4:$B$10,Lifecycle_50yr!$E$4:$E$10,--(MOD($A23,Lifecycle_50yr!$M$4:$M$10)=0))+SUMPRODUCT(Lifecycle_50yr!$B$4:$B$10,Lifecycle_50yr!$P$4:$P$10))/8760 | C23: =IF($A23=1,$H$6,0) | D23: =SUMPRODUCT(Lifecycle_50yr!$B$4:$B$10,Lifecycle_50yr!$G$4:$G$10,--(MOD($A23,Lifecycle_50yr!$C$4:$C$10)=0)) | E23: =SUMPRODUCT(Lifecycle_50yr!$B$4:$B$10,Lifecycle_50yr!$H$4:$H$10,--(MOD($A23,Lifecycle_50yr!$M$4:$M$10)=0)) | F23: =Blend_Properties!$B$3*(1-$E$4)*Global_Assumptions!$B$16/$E$7*B23 | G23: =$E$3*Global_Assumptions!$B$13/$E$7*B23 | H23: =$B$15*B23 | I23: =($B$11+$B$14)*B23+$B$12+$B$13 | J23: =$E$3*Global_Assumptions!$B$66*B23 | K23: =($E$5*Global_Assumptions!$B$20+$E$3*Global_Assumptions!$B$68*(--($A23<=Global_Assumptions!$B$86)))*B23 | L23: =J23+K23-(C23+D23+E23+F23+G23+H23+I23) | M23: =L23/(1+Global_Assumptions!$B$7)^$A23
A24: 7 | B24: =1-MIN(8760,SUMPRODUCT(Lifecycle_50yr!$B$4:$B$10,Lifecycle_50yr!$F$4:$F$10,--(MOD($A24,Lifecycle_50yr!$C$4:$C$10)=0))+SUMPRODUCT(Lifecycle_50yr!$B$4:$B$10,Lifecycle_50yr!$E$4:$E$10,--(MOD($A24,Lifecycle_50yr!$M$4:$M$10)=0))+SUMPRODUCT(Lifecycle_50yr!$B$4:$B$10,Lifecycle_50yr!$P$4:$P$10))/8760 | C24: =IF($A24=1,$H$6,0) | D24: =SUMPRODUCT(Lifecycle_50yr!$B$4:$B$10,Lifecycle_50yr!$G$4:$G$10,--(MOD($A24,Lifecycle_50yr!$C$4:$C$10)=0)) | E24: =SUMPRODUCT(Lifecycle_50yr!$B$4:$B$10,Lifecycle_50yr!$H$4:$H$10,--(MOD($A24,Lifecycle_50yr!$M$4:$M$10)=0)) | F24: =Blend_Properties!$B$3*(1-$E$4)*Global_Assumptions!$B$16/$E$7*B24 | G24: =$E$3*Global_Assumptions!$B$13/$E$7*B24 | H24: =$B$15*B24 | I24: =($B$11+$B$14)*B24+$B$12+$B$13 | J24: =$E$3*Global_Assumptions!$B$66*B24 | K24: =($E$5*Global_Assumptions!$B$20+$E$3*Global_Assumptions!$B$68*(--($A24<=Global_Assumptions!$B$86)))*B24 | L24: =J24+K24-(C24+D24+E24+F24+G24+H24+I24) | M24: =L24/(1+Global_Assumptions!$B$7)^$A24
A25: 8 | B25: =1-MIN(8760,SUMPRODUCT(Lifecycle_50yr!$B$4:$B$10,Lifecycle_50yr!$F$4:$F$10,--(MOD($A25,Lifecycle_50yr!$C$4:$C$10)=0))+SUMPRODUCT(Lifecycle_50yr!$B$4:$B$10,Lifecycle_50yr!$E$4:$E$10,--(MOD($A25,Lifecycle_50yr!$M$4:$M$10)=0))+SUMPRODUCT(Lifecycle_50yr!$B$4:$B$10,Lifecycle_50yr!$P$4:$P$10))/8760 | C25: =IF($A25=1,$H$6,0) | D25: =SUMPRODUCT(Lifecycle_50yr!$B$4:$B$10,Lifecycle_50yr!$G$4:$G$10,--(MOD($A25,Lifecycle_50yr!$C$4:$C$10)=0)) | E25: =SUMPRODUCT(Lifecycle_50yr!$B$4:$B$10,Lifecycle_50yr!$H$4:$H$10,--(MOD($A25,Lifecycle_50yr!$M$4:$M$10)=0)) | F25: =Blend_Properties!$B$3*(1-$E$4)*Global_Assumptions!$B$16/$E$7*B25 | G25: =$E$3*Global_Assumptions!$B$13/$E$7*B25 | H25: =$B$15*B25 | I25: =($B$11+$B$14)*B25+$B$12+$B$13 | J25: =$E$3*Global_Assumptions!$B$66*B25 | K25: =($E$5*Global_Assumptions!$B$20+$E$3*Global_Assumptions!$B$68*(--($A25<=Global_Assumptions!$B$86)))*B25 | L25: =J25+K25-(C25+D25+E25+F25+G25+H25+I25) | M25: =L25/(1+Global_Assumptions!$B$7)^$A25
A26: 9 | B26: =1-MIN(8760,SUMPRODUCT(Lifecycle_50yr!$B$4:$B$10,Lifecycle_50yr!$F$4:$F$10,--(MOD($A26,Lifecycle_50yr!$C$4:$C$10)=0))+SUMPRODUCT(Lifecycle_50yr!$B$4:$B$10,Lifecycle_50yr!$E$4:$E$10,--(MOD($A26,Lifecycle_50yr!$M$4:$M$10)=0))+SUMPRODUCT(Lifecycle_50yr!$B$4:$B$10,Lifecycle_50yr!$P$4:$P$10))/8760 | C26: =IF($A26=1,$H$6,0) | D26: =SUMPRODUCT(Lifecycle_50yr!$B$4:$B$10,Lifecycle_50yr!$G$4:$G$10,--(MOD($A26,Lifecycle_50yr!$C$4:$C$10)=0)) | E26: =SUMPRODUCT(Lifecycle_50yr!$B$4:$B$10,Lifecycle_50yr!$H$4:$H$10,--(MOD($A26,Lifecycle_50yr!$M$4:$M$10)=0)) | F26: =Blend_Properties!$B$3*(1-$E$4)*Global_Assumptions!$B$16/$E$7*B26 | G26: =$E$3*Global_Assumptions!$B$13/$E$7*B26 | H26: =$B$15*B26 | I26: =($B$11+$B$14)*B26+$B$12+$B$13 | J26: =$E$3*Global_Assumptions!$B$66*B26 | K26: =($E$5*Global_Assumptions!$B$20+$E$3*Global_Assumptions!$B$68*(--($A26<=Global_Assumptions!$B$86)))*B26 | L26: =J26+K26-(C26+D26+E26+F26+G26+H26+I26) | M26: =L26/(1+Global_Assumptions!$B$7)^$A26
A27: 10 | B27: =1-MIN(8760,SUMPRODUCT(Lifecycle_50yr!$B$4:$B$10,Lifecycle_50yr!$F$4:$F$10,--(MOD($A27,Lifecycle_50yr!$C$4:$C$10)=0))+SUMPRODUCT(Lifecycle_50yr!$B$4:$B$10,Lifecycle_50yr!$E$4:$E$10,--(MOD($A27,Lifecycle_50yr!$M$4:$M$10)=0))+SUMPRODUCT(Lifecycle_50yr!$B$4:$B$10,Lifecycle_50yr!$P$4:$P$10))/8760 | C27: =IF($A27=1,$H$6,0) | D27: =SUMPRODUCT(Lifecycle_50yr!$B$4:$B$10,Lifecycle_50yr!$G$4:$G$10,--(MOD($A27,Lifecycle_50yr!$C$4:$C$10)=0)) | E27: =SUMPRODUCT(Lifecycle_50yr!$B$4:$B$10,Lifecycle_50yr!$H$4:$H$10,--(MOD($A27,Lifecycle_50yr!$M$4:$M$10)=0)) | F27: =Blend_Properties!$B$3*(1-$E$4)*Global_Assumptions!$B$16/$E$7*B27 | G27: =$E$3*Global_Assumptions!$B$13/$E$7*B27 | H27: =$B$15*B27 | I27: =($B$11+$B$14)*B27+$B$12+$B$13 | J27: =$E$3*Global_Assumptions!$B$66*B27 | K27: =($E$5*Global_Assumptions!$B$20+$E$3*Global_Assumptions!$B$68*(--($A27<=Global_Assumptions!$B$86)))*B27 | L27: =J27+K27-(C27+D27+E27+F27+G27+H27+I27) | M27: =L27/(1+Global_Assumptions!$B$7)^$A27
A28: 11 | B28: =1-MIN(8760,SUMPRODUCT(Lifecycle_50yr!$B$4:$B$10,Lifecycle_50yr!$F$4:$F$10,--(MOD($A28,Lifecycle_50yr!$C$4:$C$10)=0))+SUMPRODUCT(Lifecycle_50yr!$B$4:$B$10,Lifecycle_50yr!$E$4:$E$10,--(MOD($A28,Lifecycle_50yr!$M$4:$M$10)=0))+SUMPRODUCT(Lifecycle_50yr!$B$4:$B$10,Lifecycle_50yr!$P$4:$P$10))/8760 | C28: =IF($A28=1,$H$6,0) | D28: =SUMPRODUCT(Lifecycle_50yr!$B$4:$B$10,Lifecycle_50yr!$G$4:$G$10,--(MOD($A28,Lifecycle_50yr!$C$4:$C$10)=0)) | E28: =SUMPRODUCT(Lifecycle_50yr!$B$4:$B$10,Lifecycle_50yr!$H$4:$H$10,--(MOD($A28,Lifecycle_50yr!$M$4:$M$10)=0)) | F28: =Blend_Properties!$B$3*(1-$E$4)*Global_Assumptions!$B$16/$E$7*B28 | G28: =$E$3*Global_Assumptions!$B$13/$E$7*B28 | H28: =$B$15*B28 | I28: =($B$11+$B$14)*B28+$B$12+$B$13 | J28: =$E$3*Global_Assumptions!$B$66*B28 | K28: =($E$5*Global_Assumptions!$B$20+$E$3*Global_Assumptions!$B$68*(--($A28<=Global_Assumptions!$B$86)))*B28 | L28: =J28+K28-(C28+D28+E28+F28+G28+H28+I28) | M28: =L28/(1+Global_Assumptions!$B$7)^$A28
A29: 12 | B29: =1-MIN(8760,SUMPRODUCT(Lifecycle_50yr!$B$4:$B$10,Lifecycle_50yr!$F$4:$F$10,--(MOD($A29,Lifecycle_50yr!$C$4:$C$10)=0))+SUMPRODUCT(Lifecycle_50yr!$B$4:$B$10,Lifecycle_50yr!$E$4:$E$10,--(MOD($A29,Lifecycle_50yr!$M$4:$M$10)=0))+SUMPRODUCT(Lifecycle_50yr!$B$4:$B$10,Lifecycle_50yr!$P$4:$P$10))/8760 | C29: =IF($A29=1,$H$6,0) | D29: =SUMPRODUCT(Lifecycle_50yr!$B$4:$B$10,Lifecycle_50yr!$G$4:$G$10,--(MOD($A29,Lifecycle_50yr!$C$4:$C$10)=0)) | E29: =SUMPRODUCT(Lifecycle_50yr!$B$4:$B$10,Lifecycle_50yr!$H$4:$H$10,--(MOD($A29,Lifecycle_50yr!$M$4:$M$10)=0)) | F29: =Blend_Properties!$B$3*(1-$E$4)*Global_Assumptions!$B$16/$E$7*B29 | G29: =$E$3*Global_Assumptions!$B$13/$E$7*B29 | H29: =$B$15*B29 | I29: =($B$11+$B$14)*B29+$B$12+$B$13 | J29: =$E$3*Global_Assumptions!$B$66*B29 | K29: =($E$5*Global_Assumptions!$B$20+$E$3*Global_Assumptions!$B$68*(--($A29<=Global_Assumptions!$B$86)))*B29 | L29: =J29+K29-(C29+D29+E29+F29+G29+H29+I29) | M29: =L29/(1+Global_Assumptions!$B$7)^$A29
... A67: 50 | B67: =1-MIN(8760,SUMPRODUCT(Lifecycle_50yr!$B$4:$B$10,Lifecycle_50yr!$F$4:$F$10,--(MOD($A67,Lifecycle_50yr!$C$4:$C$10)=0))+SUMPRODUCT(Lifecycle_50yr!$B$4:$B$10,Lifecycle_50yr!$E$4:$E$10,--(MOD($A67,Lifecycle_50yr!$M$4:$M$10)=0))+SUMPRODUCT(Lifecycle_50yr!$B$4:$B$10,Lifecycle_50yr!$P$4:$P$10))/8760 | C67: =IF($A67=1,$H$6,0) | D67: =SUMPRODUCT(Lifecycle_50yr!$B$4:$B$10,Lifecycle_50yr!$G$4:$G$10,--(MOD($A67,Lifecycle_50yr!$C$4:$C$10)=0)) | E67: =SUMPRODUCT(Lifecycle_50yr!$B$4:$B$10,Lifecycle_50yr!$H$4:$H$10,--(MOD($A67,Lifecycle_50yr!$M$4:$M$10)=0)) | F67: =Blend_Properties!$B$3*(1-$E$4)*Global_Assumptions!$B$16/$E$7*B67 | G67: =$E$3*Global_Assumptions!$B$13/$E$7*B67 | H67: =$B$15*B67 | I67: =($B$11+$B$14)*B67+$B$12+$B$13 | J67: =$E$3*Global_Assumptions!$B$66*B67 | K67: =($E$5*Global_Assumptions!$B$20+$E$3*Global_Assumptions!$B$68*(--($A67<=Global_Assumptions!$B$86)))*B67 | L67: =J67+K67-(C67+D67+E67+F67+G67+H67+I67) | M67: =L67/(1+Global_Assumptions!$B$7)^$A67
A69: NPV (net, $) | M69: =SUM(M18:M67)
A70: Undiscounted net 50-yr ($) | L70: =SUM(L18:L67)
A71: Mean availability (50-yr) | B71: =AVERAGE(B18:B67)

Sheet NPV_Comparison
A1: NPV COMPARISON ACROSS SCENARIOS — UCI Microturbine
A2: Screening NPV. Lead with the INCREMENTAL column (vs the 0% fossil baseline); the 0% incremental NPV is zero by construction. Absolute NPV is retained for continuity only and is non-decision-grade (end-use benefit = avoided electricity/heat, not modelled here; transmission uses a merchant revenue proxy).
A3: Annuity factor (50 yr) | B3: =(1-(1+Global_Assumptions!$B$7)^-Global_Assumptions!$B$63)/Global_Assumptions!$B$7 | D3: Mean availability | E3: =Lifecycle_50yr!$B$15
A5: A. NPV vs blend (near injection, retrofit)
A6: Scenario | B6: CAPEX ($) | C6: Annual net ($/yr) | D6: Absolute NPV 50yr ($) — non-decision-grade | E6: Avail. | F6: Incremental NPV vs 0% ($) — decision-relevant
A7: 0% near retrofit | B7: =(SUMIFS(Scenario_Results!$F$4:$F$27,Scenario_Results!$A$4:$A$27,0,Scenario_Results!$B$4:$B$27,TEA_Hydraulics!$B$3,Scenario_Results!$C$4:$C$27,"retrofit")+SUMIFS(Scenario_Results!$G$4:$G$27,Scenario_Results!$A$4:$A$27,0,Scenario_Results!$B$4:$B$27,TEA_Hydraulics!$B$3,Scenario_Results!$C$4:$C$27,"retrofit")+SUMIFS(Scenario_Results!$H$4:$H$27,Scenario_Results!$A$4:$A$27,0,Scenario_Results!$B$4:$B$27,TEA_Hydraulics!$B$3,Scenario_Results!$C$4:$C$27,"retrofit")) | C7: =(INDEX(Blend_Properties!$F$6:$F$13,MATCH(0,Blend_Properties!$A$6:$A$13,0))*Global_Assumptions!$B$66*Lifecycle_50yr!$B$15)+((INDEX(Blend_Properties!$G$6:$G$13,MATCH(0,Blend_Properties!$A$6:$A$13,0))*Global_Assumptions!$B$20+INDEX(Blend_Properties!$F$6:$F$13,MATCH(0,Blend_Properties!$A$6:$A$13,0))*Global_Assumptions!$B$68)*Lifecycle_50yr!$B$15)-(Lifecycle_50yr!$B$18+Lifecycle_50yr!$B$19+(Blend_Properties!$B$3*(1-INDEX(Blend_Properties!$B$6:$B$13,MATCH(0,Blend_Properties!$A$6:$A$13,0)))*Global_Assumptions!$B$16/(1+Global_Assumptions!$B$64*(0/100))*Lifecycle_50yr!$B$15)+(INDEX(Blend_Properties!$F$6:$F$13,MATCH(0,Blend_Properties!$A$6:$A$13,0))*Global_Assumptions!$B$13/(1+Global_Assumptions!$B$64*(0/100))*Lifecycle_50yr!$B$15)+(INDEX(Blend_Properties!$F$6:$F$13,MATCH(0,Blend_Properties!$A$6:$A$13,0))/365*Global_Assumptions!$B$49*Global_Assumptions!$B$48*Global_Assumptions!$B$65*Lifecycle_50yr!$B$15)+((INDEX(Blend_Properties!$F$6:$F$13,MATCH(0,Blend_Properties!$A$6:$A$13,0))*Global_Assumptions!$B$38*Global_Assumptions!$B$19+0.15*INDEX(Blend_Properties!$F$6:$F$13,MATCH(0,Blend_Properties!$A$6:$A$13,0)))*Lifecycle_50yr!$B$15+SUMIFS(Scenario_Results!$G$4:$G$27,Scenario_Results!$A$4:$A$27,0,Scenario_Results!$B$4:$B$27,TEA_Hydraulics!$B$3,Scenario_Results!$C$4:$C$27,"retrofit")*Global_Assumptions!$B$41+SUMIFS(Scenario_Results!$F$4:$F$27,Scenario_Results!$A$4:$A$27,0,Scenario_Results!$B$4:$B$27,TEA_Hydraulics!$B$3,Scenario_Results!$C$4:$C$27,"retrofit")*Global_Assumptions!$B$50)) | D7: =-B7+C7*$B$3 | E7: =Lifecycle_50yr!$B$15 | F7: =D7-$D$7
A8: 5% near retrofit | B8: =(SUMIFS(Scenario_Results!$F$4:$F$27,Scenario_Results!$A$4:$A$27,5,Scenario_Results!$B$4:$B$27,TEA_Hydraulics!$B$3,Scenario_Results!$C$4:$C$27,"retrofit")+SUMIFS(Scenario_Results!$G$4:$G$27,Scenario_Results!$A$4:$A$27,5,Scenario_Results!$B$4:$B$27,TEA_Hydraulics!$B$3,Scenario_Results!$C$4:$C$27,"retrofit")+SUMIFS(Scenario_Results!$H$4:$H$27,Scenario_Results!$A$4:$A$27,5,Scenario_Results!$B$4:$B$27,TEA_Hydraulics!$B$3,Scenario_Results!$C$4:$C$27,"retrofit")) | C8: =(INDEX(Blend_Properties!$F$6:$F$13,MATCH(5,Blend_Properties!$A$6:$A$13,0))*Global_Assumptions!$B$66*Lifecycle_50yr!$B$15)+((INDEX(Blend_Properties!$G$6:$G$13,MATCH(5,Blend_Properties!$A$6:$A$13,0))*Global_Assumptions!$B$20+INDEX(Blend_Properties!$F$6:$F$13,MATCH(5,Blend_Properties!$A$6:$A$13,0))*Global_Assumptions!$B$68)*Lifecycle_50yr!$B$15)-(Lifecycle_50yr!$B$18+Lifecycle_50yr!$B$19+(Blend_Properties!$B$3*(1-INDEX(Blend_Properties!$B$6:$B$13,MATCH(5,Blend_Properties!$A$6:$A$13,0)))*Global_Assumptions!$B$16/(1+Global_Assumptions!$B$64*(5/100))*Lifecycle_50yr!$B$15)+(INDEX(Blend_Properties!$F$6:$F$13,MATCH(5,Blend_Properties!$A$6:$A$13,0))*Global_Assumptions!$B$13/(1+Global_Assumptions!$B$64*(5/100))*Lifecycle_50yr!$B$15)+(INDEX(Blend_Properties!$F$6:$F$13,MATCH(5,Blend_Properties!$A$6:$A$13,0))/365*Global_Assumptions!$B$49*Global_Assumptions!$B$48*Global_Assumptions!$B$65*Lifecycle_50yr!$B$15)+((INDEX(Blend_Properties!$F$6:$F$13,MATCH(5,Blend_Properties!$A$6:$A$13,0))*Global_Assumptions!$B$38*Global_Assumptions!$B$19+0.15*INDEX(Blend_Properties!$F$6:$F$13,MATCH(5,Blend_Properties!$A$6:$A$13,0)))*Lifecycle_50yr!$B$15+SUMIFS(Scenario_Results!$G$4:$G$27,Scenario_Results!$A$4:$A$27,5,Scenario_Results!$B$4:$B$27,TEA_Hydraulics!$B$3,Scenario_Results!$C$4:$C$27,"retrofit")*Global_Assumptions!$B$41+SUMIFS(Scenario_Results!$F$4:$F$27,Scenario_Results!$A$4:$A$27,5,Scenario_Results!$B$4:$B$27,TEA_Hydraulics!$B$3,Scenario_Results!$C$4:$C$27,"retrofit")*Global_Assumptions!$B$50)) | D8: =-B8+C8*$B$3 | E8: =Lifecycle_50yr!$B$15 | F8: =D8-$D$7
A9: 10% near retrofit | B9: =(SUMIFS(Scenario_Results!$F$4:$F$27,Scenario_Results!$A$4:$A$27,10,Scenario_Results!$B$4:$B$27,TEA_Hydraulics!$B$3,Scenario_Results!$C$4:$C$27,"retrofit")+SUMIFS(Scenario_Results!$G$4:$G$27,Scenario_Results!$A$4:$A$27,10,Scenario_Results!$B$4:$B$27,TEA_Hydraulics!$B$3,Scenario_Results!$C$4:$C$27,"retrofit")+SUMIFS(Scenario_Results!$H$4:$H$27,Scenario_Results!$A$4:$A$27,10,Scenario_Results!$B$4:$B$27,TEA_Hydraulics!$B$3,Scenario_Results!$C$4:$C$27,"retrofit")) | C9: =(INDEX(Blend_Properties!$F$6:$F$13,MATCH(10,Blend_Properties!$A$6:$A$13,0))*Global_Assumptions!$B$66*Lifecycle_50yr!$B$15)+((INDEX(Blend_Properties!$G$6:$G$13,MATCH(10,Blend_Properties!$A$6:$A$13,0))*Global_Assumptions!$B$20+INDEX(Blend_Properties!$F$6:$F$13,MATCH(10,Blend_Properties!$A$6:$A$13,0))*Global_Assumptions!$B$68)*Lifecycle_50yr!$B$15)-(Lifecycle_50yr!$B$18+Lifecycle_50yr!$B$19+(Blend_Properties!$B$3*(1-INDEX(Blend_Properties!$B$6:$B$13,MATCH(10,Blend_Properties!$A$6:$A$13,0)))*Global_Assumptions!$B$16/(1+Global_Assumptions!$B$64*(10/100))*Lifecycle_50yr!$B$15)+(INDEX(Blend_Properties!$F$6:$F$13,MATCH(10,Blend_Properties!$A$6:$A$13,0))*Global_Assumptions!$B$13/(1+Global_Assumptions!$B$64*(10/100))*Lifecycle_50yr!$B$15)+(INDEX(Blend_Properties!$F$6:$F$13,MATCH(10,Blend_Properties!$A$6:$A$13,0))/365*Global_Assumptions!$B$49*Global_Assumptions!$B$48*Global_Assumptions!$B$65*Lifecycle_50yr!$B$15)+((INDEX(Blend_Properties!$F$6:$F$13,MATCH(10,Blend_Properties!$A$6:$A$13,0))*Global_Assumptions!$B$38*Global_Assumptions!$B$19+0.15*INDEX(Blend_Properties!$F$6:$F$13,MATCH(10,Blend_Properties!$A$6:$A$13,0)))*Lifecycle_50yr!$B$15+SUMIFS(Scenario_Results!$G$4:$G$27,Scenario_Results!$A$4:$A$27,10,Scenario_Results!$B$4:$B$27,TEA_Hydraulics!$B$3,Scenario_Results!$C$4:$C$27,"retrofit")*Global_Assumptions!$B$41+SUMIFS(Scenario_Results!$F$4:$F$27,Scenario_Results!$A$4:$A$27,10,Scenario_Results!$B$4:$B$27,TEA_Hydraulics!$B$3,Scenario_Results!$C$4:$C$27,"retrofit")*Global_Assumptions!$B$50)) | D9: =-B9+C9*$B$3 | E9: =Lifecycle_50yr!$B$15 | F9: =D9-$D$7
A10: 20% near retrofit | B10: =(SUMIFS(Scenario_Results!$F$4:$F$27,Scenario_Results!$A$4:$A$27,20,Scenario_Results!$B$4:$B$27,TEA_Hydraulics!$B$3,Scenario_Results!$C$4:$C$27,"retrofit")+SUMIFS(Scenario_Results!$G$4:$G$27,Scenario_Results!$A$4:$A$27,20,Scenario_Results!$B$4:$B$27,TEA_Hydraulics!$B$3,Scenario_Results!$C$4:$C$27,"retrofit")+SUMIFS(Scenario_Results!$H$4:$H$27,Scenario_Results!$A$4:$A$27,20,Scenario_Results!$B$4:$B$27,TEA_Hydraulics!$B$3,Scenario_Results!$C$4:$C$27,"retrofit")) | C10: =(INDEX(Blend_Properties!$F$6:$F$13,MATCH(20,Blend_Properties!$A$6:$A$13,0))*Global_Assumptions!$B$66*Lifecycle_50yr!$B$15)+((INDEX(Blend_Properties!$G$6:$G$13,MATCH(20,Blend_Properties!$A$6:$A$13,0))*Global_Assumptions!$B$20+INDEX(Blend_Properties!$F$6:$F$13,MATCH(20,Blend_Properties!$A$6:$A$13,0))*Global_Assumptions!$B$68)*Lifecycle_50yr!$B$15)-(Lifecycle_50yr!$B$18+Lifecycle_50yr!$B$19+(Blend_Properties!$B$3*(1-INDEX(Blend_Properties!$B$6:$B$13,MATCH(20,Blend_Properties!$A$6:$A$13,0)))*Global_Assumptions!$B$16/(1+Global_Assumptions!$B$64*(20/100))*Lifecycle_50yr!$B$15)+(INDEX(Blend_Properties!$F$6:$F$13,MATCH(20,Blend_Properties!$A$6:$A$13,0))*Global_Assumptions!$B$13/(1+Global_Assumptions!$B$64*(20/100))*Lifecycle_50yr!$B$15)+(INDEX(Blend_Properties!$F$6:$F$13,MATCH(20,Blend_Properties!$A$6:$A$13,0))/365*Global_Assumptions!$B$49*Global_Assumptions!$B$48*Global_Assumptions!$B$65*Lifecycle_50yr!$B$15)+((INDEX(Blend_Properties!$F$6:$F$13,MATCH(20,Blend_Properties!$A$6:$A$13,0))*Global_Assumptions!$B$38*Global_Assumptions!$B$19+0.15*INDEX(Blend_Properties!$F$6:$F$13,MATCH(20,Blend_Properties!$A$6:$A$13,0)))*Lifecycle_50yr!$B$15+SUMIFS(Scenario_Results!$G$4:$G$27,Scenario_Results!$A$4:$A$27,20,Scenario_Results!$B$4:$B$27,TEA_Hydraulics!$B$3,Scenario_Results!$C$4:$C$27,"retrofit")*Global_Assumptions!$B$41+SUMIFS(Scenario_Results!$F$4:$F$27,Scenario_Results!$A$4:$A$27,20,Scenario_Results!$B$4:$B$27,TEA_Hydraulics!$B$3,Scenario_Results!$C$4:$C$27,"retrofit")*Global_Assumptions!$B$50)) | D10: =-B10+C10*$B$3 | E10: =Lifecycle_50yr!$B$15 | F10: =D10-$D$7
A11: 30% near retrofit | B11: =(SUMIFS(Scenario_Results!$F$4:$F$27,Scenario_Results!$A$4:$A$27,30,Scenario_Results!$B$4:$B$27,TEA_Hydraulics!$B$3,Scenario_Results!$C$4:$C$27,"retrofit")+SUMIFS(Scenario_Results!$G$4:$G$27,Scenario_Results!$A$4:$A$27,30,Scenario_Results!$B$4:$B$27,TEA_Hydraulics!$B$3,Scenario_Results!$C$4:$C$27,"retrofit")+SUMIFS(Scenario_Results!$H$4:$H$27,Scenario_Results!$A$4:$A$27,30,Scenario_Results!$B$4:$B$27,TEA_Hydraulics!$B$3,Scenario_Results!$C$4:$C$27,"retrofit")) | C11: =(INDEX(Blend_Properties!$F$6:$F$13,MATCH(30,Blend_Properties!$A$6:$A$13,0))*Global_Assumptions!$B$66*Lifecycle_50yr!$B$15)+((INDEX(Blend_Properties!$G$6:$G$13,MATCH(30,Blend_Properties!$A$6:$A$13,0))*Global_Assumptions!$B$20+INDEX(Blend_Properties!$F$6:$F$13,MATCH(30,Blend_Properties!$A$6:$A$13,0))*Global_Assumptions!$B$68)*Lifecycle_50yr!$B$15)-(Lifecycle_50yr!$B$18+Lifecycle_50yr!$B$19+(Blend_Properties!$B$3*(1-INDEX(Blend_Properties!$B$6:$B$13,MATCH(30,Blend_Properties!$A$6:$A$13,0)))*Global_Assumptions!$B$16/(1+Global_Assumptions!$B$64*(30/100))*Lifecycle_50yr!$B$15)+(INDEX(Blend_Properties!$F$6:$F$13,MATCH(30,Blend_Properties!$A$6:$A$13,0))*Global_Assumptions!$B$13/(1+Global_Assumptions!$B$64*(30/100))*Lifecycle_50yr!$B$15)+(INDEX(Blend_Properties!$F$6:$F$13,MATCH(30,Blend_Properties!$A$6:$A$13,0))/365*Global_Assumptions!$B$49*Global_Assumptions!$B$48*Global_Assumptions!$B$65*Lifecycle_50yr!$B$15)+((INDEX(Blend_Properties!$F$6:$F$13,MATCH(30,Blend_Properties!$A$6:$A$13,0))*Global_Assumptions!$B$38*Global_Assumptions!$B$19+0.15*INDEX(Blend_Properties!$F$6:$F$13,MATCH(30,Blend_Properties!$A$6:$A$13,0)))*Lifecycle_50yr!$B$15+SUMIFS(Scenario_Results!$G$4:$G$27,Scenario_Results!$A$4:$A$27,30,Scenario_Results!$B$4:$B$27,TEA_Hydraulics!$B$3,Scenario_Results!$C$4:$C$27,"retrofit")*Global_Assumptions!$B$41+SUMIFS(Scenario_Results!$F$4:$F$27,Scenario_Results!$A$4:$A$27,30,Scenario_Results!$B$4:$B$27,TEA_Hydraulics!$B$3,Scenario_Results!$C$4:$C$27,"retrofit")*Global_Assumptions!$B$50)) | D11: =-B11+C11*$B$3 | E11: =Lifecycle_50yr!$B$15 | F11: =D11-$D$7
A12: 50% near retrofit | B12: =(SUMIFS(Scenario_Results!$F$4:$F$27,Scenario_Results!$A$4:$A$27,50,Scenario_Results!$B$4:$B$27,TEA_Hydraulics!$B$3,Scenario_Results!$C$4:$C$27,"retrofit")+SUMIFS(Scenario_Results!$G$4:$G$27,Scenario_Results!$A$4:$A$27,50,Scenario_Results!$B$4:$B$27,TEA_Hydraulics!$B$3,Scenario_Results!$C$4:$C$27,"retrofit")+SUMIFS(Scenario_Results!$H$4:$H$27,Scenario_Results!$A$4:$A$27,50,Scenario_Results!$B$4:$B$27,TEA_Hydraulics!$B$3,Scenario_Results!$C$4:$C$27,"retrofit")) | C12: =(INDEX(Blend_Properties!$F$6:$F$13,MATCH(50,Blend_Properties!$A$6:$A$13,0))*Global_Assumptions!$B$66*Lifecycle_50yr!$B$15)+((INDEX(Blend_Properties!$G$6:$G$13,MATCH(50,Blend_Properties!$A$6:$A$13,0))*Global_Assumptions!$B$20+INDEX(Blend_Properties!$F$6:$F$13,MATCH(50,Blend_Properties!$A$6:$A$13,0))*Global_Assumptions!$B$68)*Lifecycle_50yr!$B$15)-(Lifecycle_50yr!$B$18+Lifecycle_50yr!$B$19+(Blend_Properties!$B$3*(1-INDEX(Blend_Properties!$B$6:$B$13,MATCH(50,Blend_Properties!$A$6:$A$13,0)))*Global_Assumptions!$B$16/(1+Global_Assumptions!$B$64*(50/100))*Lifecycle_50yr!$B$15)+(INDEX(Blend_Properties!$F$6:$F$13,MATCH(50,Blend_Properties!$A$6:$A$13,0))*Global_Assumptions!$B$13/(1+Global_Assumptions!$B$64*(50/100))*Lifecycle_50yr!$B$15)+(INDEX(Blend_Properties!$F$6:$F$13,MATCH(50,Blend_Properties!$A$6:$A$13,0))/365*Global_Assumptions!$B$49*Global_Assumptions!$B$48*Global_Assumptions!$B$65*Lifecycle_50yr!$B$15)+((INDEX(Blend_Properties!$F$6:$F$13,MATCH(50,Blend_Properties!$A$6:$A$13,0))*Global_Assumptions!$B$38*Global_Assumptions!$B$19+0.15*INDEX(Blend_Properties!$F$6:$F$13,MATCH(50,Blend_Properties!$A$6:$A$13,0)))*Lifecycle_50yr!$B$15+SUMIFS(Scenario_Results!$G$4:$G$27,Scenario_Results!$A$4:$A$27,50,Scenario_Results!$B$4:$B$27,TEA_Hydraulics!$B$3,Scenario_Results!$C$4:$C$27,"retrofit")*Global_Assumptions!$B$41+SUMIFS(Scenario_Results!$F$4:$F$27,Scenario_Results!$A$4:$A$27,50,Scenario_Results!$B$4:$B$27,TEA_Hydraulics!$B$3,Scenario_Results!$C$4:$C$27,"retrofit")*Global_Assumptions!$B$50)) | D12: =-B12+C12*$B$3 | E12: =Lifecycle_50yr!$B$15 | F12: =D12-$D$7
A13: 75% near retrofit | B13: =(SUMIFS(Scenario_Results!$F$4:$F$27,Scenario_Results!$A$4:$A$27,75,Scenario_Results!$B$4:$B$27,TEA_Hydraulics!$B$3,Scenario_Results!$C$4:$C$27,"retrofit")+SUMIFS(Scenario_Results!$G$4:$G$27,Scenario_Results!$A$4:$A$27,75,Scenario_Results!$B$4:$B$27,TEA_Hydraulics!$B$3,Scenario_Results!$C$4:$C$27,"retrofit")+SUMIFS(Scenario_Results!$H$4:$H$27,Scenario_Results!$A$4:$A$27,75,Scenario_Results!$B$4:$B$27,TEA_Hydraulics!$B$3,Scenario_Results!$C$4:$C$27,"retrofit")) | C13: =(INDEX(Blend_Properties!$F$6:$F$13,MATCH(75,Blend_Properties!$A$6:$A$13,0))*Global_Assumptions!$B$66*Lifecycle_50yr!$B$15)+((INDEX(Blend_Properties!$G$6:$G$13,MATCH(75,Blend_Properties!$A$6:$A$13,0))*Global_Assumptions!$B$20+INDEX(Blend_Properties!$F$6:$F$13,MATCH(75,Blend_Properties!$A$6:$A$13,0))*Global_Assumptions!$B$68)*Lifecycle_50yr!$B$15)-(Lifecycle_50yr!$B$18+Lifecycle_50yr!$B$19+(Blend_Properties!$B$3*(1-INDEX(Blend_Properties!$B$6:$B$13,MATCH(75,Blend_Properties!$A$6:$A$13,0)))*Global_Assumptions!$B$16/(1+Global_Assumptions!$B$64*(75/100))*Lifecycle_50yr!$B$15)+(INDEX(Blend_Properties!$F$6:$F$13,MATCH(75,Blend_Properties!$A$6:$A$13,0))*Global_Assumptions!$B$13/(1+Global_Assumptions!$B$64*(75/100))*Lifecycle_50yr!$B$15)+(INDEX(Blend_Properties!$F$6:$F$13,MATCH(75,Blend_Properties!$A$6:$A$13,0))/365*Global_Assumptions!$B$49*Global_Assumptions!$B$48*Global_Assumptions!$B$65*Lifecycle_50yr!$B$15)+((INDEX(Blend_Properties!$F$6:$F$13,MATCH(75,Blend_Properties!$A$6:$A$13,0))*Global_Assumptions!$B$38*Global_Assumptions!$B$19+0.15*INDEX(Blend_Properties!$F$6:$F$13,MATCH(75,Blend_Properties!$A$6:$A$13,0)))*Lifecycle_50yr!$B$15+SUMIFS(Scenario_Results!$G$4:$G$27,Scenario_Results!$A$4:$A$27,75,Scenario_Results!$B$4:$B$27,TEA_Hydraulics!$B$3,Scenario_Results!$C$4:$C$27,"retrofit")*Global_Assumptions!$B$41+SUMIFS(Scenario_Results!$F$4:$F$27,Scenario_Results!$A$4:$A$27,75,Scenario_Results!$B$4:$B$27,TEA_Hydraulics!$B$3,Scenario_Results!$C$4:$C$27,"retrofit")*Global_Assumptions!$B$50)) | D13: =-B13+C13*$B$3 | E13: =Lifecycle_50yr!$B$15 | F13: =D13-$D$7
A14: 100% near retrofit | B14: =(SUMIFS(Scenario_Results!$F$4:$F$27,Scenario_Results!$A$4:$A$27,100,Scenario_Results!$B$4:$B$27,TEA_Hydraulics!$B$3,Scenario_Results!$C$4:$C$27,"retrofit")+SUMIFS(Scenario_Results!$G$4:$G$27,Scenario_Results!$A$4:$A$27,100,Scenario_Results!$B$4:$B$27,TEA_Hydraulics!$B$3,Scenario_Results!$C$4:$C$27,"retrofit")+SUMIFS(Scenario_Results!$H$4:$H$27,Scenario_Results!$A$4:$A$27,100,Scenario_Results!$B$4:$B$27,TEA_Hydraulics!$B$3,Scenario_Results!$C$4:$C$27,"retrofit")) | C14: =(INDEX(Blend_Properties!$F$6:$F$13,MATCH(100,Blend_Properties!$A$6:$A$13,0))*Global_Assumptions!$B$66*Lifecycle_50yr!$B$15)+((INDEX(Blend_Properties!$G$6:$G$13,MATCH(100,Blend_Properties!$A$6:$A$13,0))*Global_Assumptions!$B$20+INDEX(Blend_Properties!$F$6:$F$13,MATCH(100,Blend_Properties!$A$6:$A$13,0))*Global_Assumptions!$B$68)*Lifecycle_50yr!$B$15)-(Lifecycle_50yr!$B$18+Lifecycle_50yr!$B$19+(Blend_Properties!$B$3*(1-INDEX(Blend_Properties!$B$6:$B$13,MATCH(100,Blend_Properties!$A$6:$A$13,0)))*Global_Assumptions!$B$16/(1+Global_Assumptions!$B$64*(100/100))*Lifecycle_50yr!$B$15)+(INDEX(Blend_Properties!$F$6:$F$13,MATCH(100,Blend_Properties!$A$6:$A$13,0))*Global_Assumptions!$B$13/(1+Global_Assumptions!$B$64*(100/100))*Lifecycle_50yr!$B$15)+(INDEX(Blend_Properties!$F$6:$F$13,MATCH(100,Blend_Properties!$A$6:$A$13,0))/365*Global_Assumptions!$B$49*Global_Assumptions!$B$48*Global_Assumptions!$B$65*Lifecycle_50yr!$B$15)+((INDEX(Blend_Properties!$F$6:$F$13,MATCH(100,Blend_Properties!$A$6:$A$13,0))*Global_Assumptions!$B$38*Global_Assumptions!$B$19+0.15*INDEX(Blend_Properties!$F$6:$F$13,MATCH(100,Blend_Properties!$A$6:$A$13,0)))*Lifecycle_50yr!$B$15+SUMIFS(Scenario_Results!$G$4:$G$27,Scenario_Results!$A$4:$A$27,100,Scenario_Results!$B$4:$B$27,TEA_Hydraulics!$B$3,Scenario_Results!$C$4:$C$27,"retrofit")*Global_Assumptions!$B$41+SUMIFS(Scenario_Results!$F$4:$F$27,Scenario_Results!$A$4:$A$27,100,Scenario_Results!$B$4:$B$27,TEA_Hydraulics!$B$3,Scenario_Results!$C$4:$C$27,"retrofit")*Global_Assumptions!$B$50)) | D14: =-B14+C14*$B$3 | E14: =Lifecycle_50yr!$B$15 | F14: =D14-$D$7
A16: B. NPV vs delivery pressure (20% blend, near retrofit)
A17: Scenario | B17: CAPEX ($) | C17: Annual net ($/yr) | D17: NPV 50yr ($) | E17: Avail.
A18: 200 psig | B18: =(SUMIFS(Scenario_Results!$F$4:$F$27,Scenario_Results!$A$4:$A$27,20,Scenario_Results!$B$4:$B$27,TEA_Hydraulics!$B$3,Scenario_Results!$C$4:$C$27,"retrofit")+SUMIFS(Scenario_Results!$G$4:$G$27,Scenario_Results!$A$4:$A$27,20,Scenario_Results!$B$4:$B$27,TEA_Hydraulics!$B$3,Scenario_Results!$C$4:$C$27,"retrofit")+SUMIFS(Scenario_Results!$H$4:$H$27,Scenario_Results!$A$4:$A$27,20,Scenario_Results!$B$4:$B$27,TEA_Hydraulics!$B$3,Scenario_Results!$C$4:$C$27,"retrofit")) | C18: =(INDEX(Blend_Properties!$F$6:$F$13,MATCH(20,Blend_Properties!$A$6:$A$13,0))*Global_Assumptions!$B$66*Lifecycle_50yr!$B$15)+((INDEX(Blend_Properties!$G$6:$G$13,MATCH(20,Blend_Properties!$A$6:$A$13,0))*Global_Assumptions!$B$20+INDEX(Blend_Properties!$F$6:$F$13,MATCH(20,Blend_Properties!$A$6:$A$13,0))*Global_Assumptions!$B$68)*Lifecycle_50yr!$B$15)-(Lifecycle_50yr!$B$18+Lifecycle_50yr!$B$19+(Blend_Properties!$B$3*(1-INDEX(Blend_Properties!$B$6:$B$13,MATCH(20,Blend_Properties!$A$6:$A$13,0)))*Global_Assumptions!$B$16/(1+Global_Assumptions!$B$64*(20/100))*Lifecycle_50yr!$B$15)+(INDEX(Blend_Properties!$F$6:$F$13,MATCH(20,Blend_Properties!$A$6:$A$13,0))*Global_Assumptions!$B$13/(1+Global_Assumptions!$B$64*(20/100))*Lifecycle_50yr!$B$15)+(INDEX(Blend_Properties!$F$6:$F$13,MATCH(20,Blend_Properties!$A$6:$A$13,0))/365*Global_Assumptions!$B$49*Global_Assumptions!$B$48*Global_Assumptions!$B$65*Lifecycle_50yr!$B$15)+((INDEX(Blend_Properties!$F$6:$F$13,MATCH(20,Blend_Properties!$A$6:$A$13,0))*Global_Assumptions!$B$38*Global_Assumptions!$B$19+0.15*INDEX(Blend_Properties!$F$6:$F$13,MATCH(20,Blend_Properties!$A$6:$A$13,0)))*Lifecycle_50yr!$B$15+SUMIFS(Scenario_Results!$G$4:$G$27,Scenario_Results!$A$4:$A$27,20,Scenario_Results!$B$4:$B$27,TEA_Hydraulics!$B$3,Scenario_Results!$C$4:$C$27,"retrofit")*Global_Assumptions!$B$41+SUMIFS(Scenario_Results!$F$4:$F$27,Scenario_Results!$A$4:$A$27,20,Scenario_Results!$B$4:$B$27,TEA_Hydraulics!$B$3,Scenario_Results!$C$4:$C$27,"retrofit")*Global_Assumptions!$B$50)) | D18: =-B18+C18*$B$3 | E18: =Lifecycle_50yr!$B$15
A19: 390 psig | B19: =(SUMIFS(Scenario_Results!$F$4:$F$27,Scenario_Results!$A$4:$A$27,20,Scenario_Results!$B$4:$B$27,TEA_Hydraulics!$B$3,Scenario_Results!$C$4:$C$27,"retrofit")+SUMIFS(Scenario_Results!$G$4:$G$27,Scenario_Results!$A$4:$A$27,20,Scenario_Results!$B$4:$B$27,TEA_Hydraulics!$B$3,Scenario_Results!$C$4:$C$27,"retrofit")+SUMIFS(Scenario_Results!$H$4:$H$27,Scenario_Results!$A$4:$A$27,20,Scenario_Results!$B$4:$B$27,TEA_Hydraulics!$B$3,Scenario_Results!$C$4:$C$27,"retrofit")) | C19: =(INDEX(Blend_Properties!$F$6:$F$13,MATCH(20,Blend_Properties!$A$6:$A$13,0))*Global_Assumptions!$B$66*Lifecycle_50yr!$B$15)+((INDEX(Blend_Properties!$G$6:$G$13,MATCH(20,Blend_Properties!$A$6:$A$13,0))*Global_Assumptions!$B$20+INDEX(Blend_Properties!$F$6:$F$13,MATCH(20,Blend_Properties!$A$6:$A$13,0))*Global_Assumptions!$B$68)*Lifecycle_50yr!$B$15)-(Lifecycle_50yr!$B$18+Lifecycle_50yr!$B$19+(Blend_Properties!$B$3*(1-INDEX(Blend_Properties!$B$6:$B$13,MATCH(20,Blend_Properties!$A$6:$A$13,0)))*Global_Assumptions!$B$16/(1+Global_Assumptions!$B$64*(20/100))*Lifecycle_50yr!$B$15)+(INDEX(Blend_Properties!$F$6:$F$13,MATCH(20,Blend_Properties!$A$6:$A$13,0))*Global_Assumptions!$B$13/(1+Global_Assumptions!$B$64*(20/100))*Lifecycle_50yr!$B$15)+(INDEX(Blend_Properties!$F$6:$F$13,MATCH(20,Blend_Properties!$A$6:$A$13,0))/365*Global_Assumptions!$B$49*Global_Assumptions!$B$48*Global_Assumptions!$B$65*Lifecycle_50yr!$B$15)+((INDEX(Blend_Properties!$F$6:$F$13,MATCH(20,Blend_Properties!$A$6:$A$13,0))*Global_Assumptions!$B$38*Global_Assumptions!$B$19+0.15*INDEX(Blend_Properties!$F$6:$F$13,MATCH(20,Blend_Properties!$A$6:$A$13,0)))*Lifecycle_50yr!$B$15+SUMIFS(Scenario_Results!$G$4:$G$27,Scenario_Results!$A$4:$A$27,20,Scenario_Results!$B$4:$B$27,TEA_Hydraulics!$B$3,Scenario_Results!$C$4:$C$27,"retrofit")*Global_Assumptions!$B$41+SUMIFS(Scenario_Results!$F$4:$F$27,Scenario_Results!$A$4:$A$27,20,Scenario_Results!$B$4:$B$27,TEA_Hydraulics!$B$3,Scenario_Results!$C$4:$C$27,"retrofit")*Global_Assumptions!$B$50)) | D19: =-B19+C19*$B$3 | E19: =Lifecycle_50yr!$B$15
A20: 465 psig | B20: =(SUMIFS(Scenario_Results!$F$4:$F$27,Scenario_Results!$A$4:$A$27,20,Scenario_Results!$B$4:$B$27,TEA_Hydraulics!$B$3,Scenario_Results!$C$4:$C$27,"retrofit")+SUMIFS(Scenario_Results!$G$4:$G$27,Scenario_Results!$A$4:$A$27,20,Scenario_Results!$B$4:$B$27,TEA_Hydraulics!$B$3,Scenario_Results!$C$4:$C$27,"retrofit")+SUMIFS(Scenario_Results!$H$4:$H$27,Scenario_Results!$A$4:$A$27,20,Scenario_Results!$B$4:$B$27,TEA_Hydraulics!$B$3,Scenario_Results!$C$4:$C$27,"retrofit")) | C20: =(INDEX(Blend_Properties!$F$6:$F$13,MATCH(20,Blend_Properties!$A$6:$A$13,0))*Global_Assumptions!$B$66*Lifecycle_50yr!$B$15)+((INDEX(Blend_Properties!$G$6:$G$13,MATCH(20,Blend_Properties!$A$6:$A$13,0))*Global_Assumptions!$B$20+INDEX(Blend_Properties!$F$6:$F$13,MATCH(20,Blend_Properties!$A$6:$A$13,0))*Global_Assumptions!$B$68)*Lifecycle_50yr!$B$15)-(Lifecycle_50yr!$B$18+Lifecycle_50yr!$B$19+(Blend_Properties!$B$3*(1-INDEX(Blend_Properties!$B$6:$B$13,MATCH(20,Blend_Properties!$A$6:$A$13,0)))*Global_Assumptions!$B$16/(1+Global_Assumptions!$B$64*(20/100))*Lifecycle_50yr!$B$15)+(INDEX(Blend_Properties!$F$6:$F$13,MATCH(20,Blend_Properties!$A$6:$A$13,0))*Global_Assumptions!$B$13/(1+Global_Assumptions!$B$64*(20/100))*Lifecycle_50yr!$B$15)+(INDEX(Blend_Properties!$F$6:$F$13,MATCH(20,Blend_Properties!$A$6:$A$13,0))/365*Global_Assumptions!$B$49*Global_Assumptions!$B$48*Global_Assumptions!$B$65*Lifecycle_50yr!$B$15)+((INDEX(Blend_Properties!$F$6:$F$13,MATCH(20,Blend_Properties!$A$6:$A$13,0))*Global_Assumptions!$B$38*Global_Assumptions!$B$19+0.15*INDEX(Blend_Properties!$F$6:$F$13,MATCH(20,Blend_Properties!$A$6:$A$13,0)))*Lifecycle_50yr!$B$15+SUMIFS(Scenario_Results!$G$4:$G$27,Scenario_Results!$A$4:$A$27,20,Scenario_Results!$B$4:$B$27,TEA_Hydraulics!$B$3,Scenario_Results!$C$4:$C$27,"retrofit")*Global_Assumptions!$B$41+SUMIFS(Scenario_Results!$F$4:$F$27,Scenario_Results!$A$4:$A$27,20,Scenario_Results!$B$4:$B$27,TEA_Hydraulics!$B$3,Scenario_Results!$C$4:$C$27,"retrofit")*Global_Assumptions!$B$50)) | D20: =-B20+C20*$B$3 | E20: =Lifecycle_50yr!$B$15
A21: 600 psig | B21: =(SUMIFS(Scenario_Results!$F$4:$F$27,Scenario_Results!$A$4:$A$27,20,Scenario_Results!$B$4:$B$27,TEA_Hydraulics!$B$3,Scenario_Results!$C$4:$C$27,"retrofit")+SUMIFS(Scenario_Results!$G$4:$G$27,Scenario_Results!$A$4:$A$27,20,Scenario_Results!$B$4:$B$27,TEA_Hydraulics!$B$3,Scenario_Results!$C$4:$C$27,"retrofit")+SUMIFS(Scenario_Results!$H$4:$H$27,Scenario_Results!$A$4:$A$27,20,Scenario_Results!$B$4:$B$27,TEA_Hydraulics!$B$3,Scenario_Results!$C$4:$C$27,"retrofit")) | C21: =(INDEX(Blend_Properties!$F$6:$F$13,MATCH(20,Blend_Properties!$A$6:$A$13,0))*Global_Assumptions!$B$66*Lifecycle_50yr!$B$15)+((INDEX(Blend_Properties!$G$6:$G$13,MATCH(20,Blend_Properties!$A$6:$A$13,0))*Global_Assumptions!$B$20+INDEX(Blend_Properties!$F$6:$F$13,MATCH(20,Blend_Properties!$A$6:$A$13,0))*Global_Assumptions!$B$68)*Lifecycle_50yr!$B$15)-(Lifecycle_50yr!$B$18+Lifecycle_50yr!$B$19+(Blend_Properties!$B$3*(1-INDEX(Blend_Properties!$B$6:$B$13,MATCH(20,Blend_Properties!$A$6:$A$13,0)))*Global_Assumptions!$B$16/(1+Global_Assumptions!$B$64*(20/100))*Lifecycle_50yr!$B$15)+(INDEX(Blend_Properties!$F$6:$F$13,MATCH(20,Blend_Properties!$A$6:$A$13,0))*Global_Assumptions!$B$13/(1+Global_Assumptions!$B$64*(20/100))*Lifecycle_50yr!$B$15)+(INDEX(Blend_Properties!$F$6:$F$13,MATCH(20,Blend_Properties!$A$6:$A$13,0))/365*Global_Assumptions!$B$49*Global_Assumptions!$B$48*Global_Assumptions!$B$65*Lifecycle_50yr!$B$15)+((INDEX(Blend_Properties!$F$6:$F$13,MATCH(20,Blend_Properties!$A$6:$A$13,0))*Global_Assumptions!$B$38*Global_Assumptions!$B$19+0.171*INDEX(Blend_Properties!$F$6:$F$13,MATCH(20,Blend_Properties!$A$6:$A$13,0)))*Lifecycle_50yr!$B$15+SUMIFS(Scenario_Results!$G$4:$G$27,Scenario_Results!$A$4:$A$27,20,Scenario_Results!$B$4:$B$27,TEA_Hydraulics!$B$3,Scenario_Results!$C$4:$C$27,"retrofit")*Global_Assumptions!$B$41+SUMIFS(Scenario_Results!$F$4:$F$27,Scenario_Results!$A$4:$A$27,20,Scenario_Results!$B$4:$B$27,TEA_Hydraulics!$B$3,Scenario_Results!$C$4:$C$27,"retrofit")*Global_Assumptions!$B$50)) | D21: =-B21+C21*$B$3 | E21: =Lifecycle_50yr!$B$15
A22: 900 psig | B22: =(SUMIFS(Scenario_Results!$F$4:$F$27,Scenario_Results!$A$4:$A$27,20,Scenario_Results!$B$4:$B$27,TEA_Hydraulics!$B$3,Scenario_Results!$C$4:$C$27,"retrofit")+SUMIFS(Scenario_Results!$G$4:$G$27,Scenario_Results!$A$4:$A$27,20,Scenario_Results!$B$4:$B$27,TEA_Hydraulics!$B$3,Scenario_Results!$C$4:$C$27,"retrofit")+SUMIFS(Scenario_Results!$H$4:$H$27,Scenario_Results!$A$4:$A$27,20,Scenario_Results!$B$4:$B$27,TEA_Hydraulics!$B$3,Scenario_Results!$C$4:$C$27,"retrofit")) | C22: =(INDEX(Blend_Properties!$F$6:$F$13,MATCH(20,Blend_Properties!$A$6:$A$13,0))*Global_Assumptions!$B$66*Lifecycle_50yr!$B$15)+((INDEX(Blend_Properties!$G$6:$G$13,MATCH(20,Blend_Properties!$A$6:$A$13,0))*Global_Assumptions!$B$20+INDEX(Blend_Properties!$F$6:$F$13,MATCH(20,Blend_Properties!$A$6:$A$13,0))*Global_Assumptions!$B$68)*Lifecycle_50yr!$B$15)-(Lifecycle_50yr!$B$18+Lifecycle_50yr!$B$19+(Blend_Properties!$B$3*(1-INDEX(Blend_Properties!$B$6:$B$13,MATCH(20,Blend_Properties!$A$6:$A$13,0)))*Global_Assumptions!$B$16/(1+Global_Assumptions!$B$64*(20/100))*Lifecycle_50yr!$B$15)+(INDEX(Blend_Properties!$F$6:$F$13,MATCH(20,Blend_Properties!$A$6:$A$13,0))*Global_Assumptions!$B$13/(1+Global_Assumptions!$B$64*(20/100))*Lifecycle_50yr!$B$15)+(INDEX(Blend_Properties!$F$6:$F$13,MATCH(20,Blend_Properties!$A$6:$A$13,0))/365*Global_Assumptions!$B$49*Global_Assumptions!$B$48*Global_Assumptions!$B$65*Lifecycle_50yr!$B$15)+((INDEX(Blend_Properties!$F$6:$F$13,MATCH(20,Blend_Properties!$A$6:$A$13,0))*Global_Assumptions!$B$38*Global_Assumptions!$B$19+0.2045*INDEX(Blend_Properties!$F$6:$F$13,MATCH(20,Blend_Properties!$A$6:$A$13,0)))*Lifecycle_50yr!$B$15+SUMIFS(Scenario_Results!$G$4:$G$27,Scenario_Results!$A$4:$A$27,20,Scenario_Results!$B$4:$B$27,TEA_Hydraulics!$B$3,Scenario_Results!$C$4:$C$27,"retrofit")*Global_Assumptions!$B$41+SUMIFS(Scenario_Results!$F$4:$F$27,Scenario_Results!$A$4:$A$27,20,Scenario_Results!$B$4:$B$27,TEA_Hydraulics!$B$3,Scenario_Results!$C$4:$C$27,"retrofit")*Global_Assumptions!$B$50)) | D22: =-B22+C22*$B$3 | E22: =Lifecycle_50yr!$B$15
A23: 1200 psig | B23: =(SUMIFS(Scenario_Results!$F$4:$F$27,Scenario_Results!$A$4:$A$27,20,Scenario_Results!$B$4:$B$27,TEA_Hydraulics!$B$3,Scenario_Results!$C$4:$C$27,"retrofit")+SUMIFS(Scenario_Results!$G$4:$G$27,Scenario_Results!$A$4:$A$27,20,Scenario_Results!$B$4:$B$27,TEA_Hydraulics!$B$3,Scenario_Results!$C$4:$C$27,"retrofit")+SUMIFS(Scenario_Results!$H$4:$H$27,Scenario_Results!$A$4:$A$27,20,Scenario_Results!$B$4:$B$27,TEA_Hydraulics!$B$3,Scenario_Results!$C$4:$C$27,"retrofit")) | C23: =(INDEX(Blend_Properties!$F$6:$F$13,MATCH(20,Blend_Properties!$A$6:$A$13,0))*Global_Assumptions!$B$66*Lifecycle_50yr!$B$15)+((INDEX(Blend_Properties!$G$6:$G$13,MATCH(20,Blend_Properties!$A$6:$A$13,0))*Global_Assumptions!$B$20+INDEX(Blend_Properties!$F$6:$F$13,MATCH(20,Blend_Properties!$A$6:$A$13,0))*Global_Assumptions!$B$68)*Lifecycle_50yr!$B$15)-(Lifecycle_50yr!$B$18+Lifecycle_50yr!$B$19+(Blend_Properties!$B$3*(1-INDEX(Blend_Properties!$B$6:$B$13,MATCH(20,Blend_Properties!$A$6:$A$13,0)))*Global_Assumptions!$B$16/(1+Global_Assumptions!$B$64*(20/100))*Lifecycle_50yr!$B$15)+(INDEX(Blend_Properties!$F$6:$F$13,MATCH(20,Blend_Properties!$A$6:$A$13,0))*Global_Assumptions!$B$13/(1+Global_Assumptions!$B$64*(20/100))*Lifecycle_50yr!$B$15)+(INDEX(Blend_Properties!$F$6:$F$13,MATCH(20,Blend_Properties!$A$6:$A$13,0))/365*Global_Assumptions!$B$49*Global_Assumptions!$B$48*Global_Assumptions!$B$65*Lifecycle_50yr!$B$15)+((INDEX(Blend_Properties!$F$6:$F$13,MATCH(20,Blend_Properties!$A$6:$A$13,0))*Global_Assumptions!$B$38*Global_Assumptions!$B$19+0.2282*INDEX(Blend_Properties!$F$6:$F$13,MATCH(20,Blend_Properties!$A$6:$A$13,0)))*Lifecycle_50yr!$B$15+SUMIFS(Scenario_Results!$G$4:$G$27,Scenario_Results!$A$4:$A$27,20,Scenario_Results!$B$4:$B$27,TEA_Hydraulics!$B$3,Scenario_Results!$C$4:$C$27,"retrofit")*Global_Assumptions!$B$41+SUMIFS(Scenario_Results!$F$4:$F$27,Scenario_Results!$A$4:$A$27,20,Scenario_Results!$B$4:$B$27,TEA_Hydraulics!$B$3,Scenario_Results!$C$4:$C$27,"retrofit")*Global_Assumptions!$B$50)) | D23: =-B23+C23*$B$3 | E23: =Lifecycle_50yr!$B$15
A24: 1500 psig | B24: =(SUMIFS(Scenario_Results!$F$4:$F$27,Scenario_Results!$A$4:$A$27,20,Scenario_Results!$B$4:$B$27,TEA_Hydraulics!$B$3,Scenario_Results!$C$4:$C$27,"retrofit")+SUMIFS(Scenario_Results!$G$4:$G$27,Scenario_Results!$A$4:$A$27,20,Scenario_Results!$B$4:$B$27,TEA_Hydraulics!$B$3,Scenario_Results!$C$4:$C$27,"retrofit")+SUMIFS(Scenario_Results!$H$4:$H$27,Scenario_Results!$A$4:$A$27,20,Scenario_Results!$B$4:$B$27,TEA_Hydraulics!$B$3,Scenario_Results!$C$4:$C$27,"retrofit")) | C24: =(INDEX(Blend_Properties!$F$6:$F$13,MATCH(20,Blend_Properties!$A$6:$A$13,0))*Global_Assumptions!$B$66*Lifecycle_50yr!$B$15)+((INDEX(Blend_Properties!$G$6:$G$13,MATCH(20,Blend_Properties!$A$6:$A$13,0))*Global_Assumptions!$B$20+INDEX(Blend_Properties!$F$6:$F$13,MATCH(20,Blend_Properties!$A$6:$A$13,0))*Global_Assumptions!$B$68)*Lifecycle_50yr!$B$15)-(Lifecycle_50yr!$B$18+Lifecycle_50yr!$B$19+(Blend_Properties!$B$3*(1-INDEX(Blend_Properties!$B$6:$B$13,MATCH(20,Blend_Properties!$A$6:$A$13,0)))*Global_Assumptions!$B$16/(1+Global_Assumptions!$B$64*(20/100))*Lifecycle_50yr!$B$15)+(INDEX(Blend_Properties!$F$6:$F$13,MATCH(20,Blend_Properties!$A$6:$A$13,0))*Global_Assumptions!$B$13/(1+Global_Assumptions!$B$64*(20/100))*Lifecycle_50yr!$B$15)+(INDEX(Blend_Properties!$F$6:$F$13,MATCH(20,Blend_Properties!$A$6:$A$13,0))/365*Global_Assumptions!$B$49*Global_Assumptions!$B$48*Global_Assumptions!$B$65*Lifecycle_50yr!$B$15)+((INDEX(Blend_Properties!$F$6:$F$13,MATCH(20,Blend_Properties!$A$6:$A$13,0))*Global_Assumptions!$B$38*Global_Assumptions!$B$19+0.2466*INDEX(Blend_Properties!$F$6:$F$13,MATCH(20,Blend_Properties!$A$6:$A$13,0)))*Lifecycle_50yr!$B$15+SUMIFS(Scenario_Results!$G$4:$G$27,Scenario_Results!$A$4:$A$27,20,Scenario_Results!$B$4:$B$27,TEA_Hydraulics!$B$3,Scenario_Results!$C$4:$C$27,"retrofit")*Global_Assumptions!$B$41+SUMIFS(Scenario_Results!$F$4:$F$27,Scenario_Results!$A$4:$A$27,20,Scenario_Results!$B$4:$B$27,TEA_Hydraulics!$B$3,Scenario_Results!$C$4:$C$27,"retrofit")*Global_Assumptions!$B$50)) | D24: =-B24+C24*$B$3 | E24: =Lifecycle_50yr!$B$15
A26: C. NPV vs pathway (20% blend, far injection)
A27: Scenario | B27: CAPEX ($) | C27: Annual net ($/yr) | D27: NPV 50yr ($) | E27: Avail.
A28: 20% far retrofit | B28: =(SUMIFS(Scenario_Results!$F$4:$F$27,Scenario_Results!$A$4:$A$27,20,Scenario_Results!$B$4:$B$27,TEA_Hydraulics!$E$3,Scenario_Results!$C$4:$C$27,"retrofit")+SUMIFS(Scenario_Results!$G$4:$G$27,Scenario_Results!$A$4:$A$27,20,Scenario_Results!$B$4:$B$27,TEA_Hydraulics!$E$3,Scenario_Results!$C$4:$C$27,"retrofit")+SUMIFS(Scenario_Results!$H$4:$H$27,Scenario_Results!$A$4:$A$27,20,Scenario_Results!$B$4:$B$27,TEA_Hydraulics!$E$3,Scenario_Results!$C$4:$C$27,"retrofit")) | C28: =(INDEX(Blend_Properties!$F$6:$F$13,MATCH(20,Blend_Properties!$A$6:$A$13,0))*Global_Assumptions!$B$66*Lifecycle_50yr!$B$15)+((INDEX(Blend_Properties!$G$6:$G$13,MATCH(20,Blend_Properties!$A$6:$A$13,0))*Global_Assumptions!$B$20+INDEX(Blend_Properties!$F$6:$F$13,MATCH(20,Blend_Properties!$A$6:$A$13,0))*Global_Assumptions!$B$68)*Lifecycle_50yr!$B$15)-(Lifecycle_50yr!$B$18+Lifecycle_50yr!$B$19+(Blend_Properties!$B$3*(1-INDEX(Blend_Properties!$B$6:$B$13,MATCH(20,Blend_Properties!$A$6:$A$13,0)))*Global_Assumptions!$B$16/(1+Global_Assumptions!$B$64*(20/100))*Lifecycle_50yr!$B$15)+(INDEX(Blend_Properties!$F$6:$F$13,MATCH(20,Blend_Properties!$A$6:$A$13,0))*Global_Assumptions!$B$13/(1+Global_Assumptions!$B$64*(20/100))*Lifecycle_50yr!$B$15)+(INDEX(Blend_Properties!$F$6:$F$13,MATCH(20,Blend_Properties!$A$6:$A$13,0))/365*Global_Assumptions!$B$49*Global_Assumptions!$B$48*Global_Assumptions!$B$65*Lifecycle_50yr!$B$15)+((INDEX(Blend_Properties!$F$6:$F$13,MATCH(20,Blend_Properties!$A$6:$A$13,0))*Global_Assumptions!$B$38*Global_Assumptions!$B$19+0.15*INDEX(Blend_Properties!$F$6:$F$13,MATCH(20,Blend_Properties!$A$6:$A$13,0)))*Lifecycle_50yr!$B$15+SUMIFS(Scenario_Results!$G$4:$G$27,Scenario_Results!$A$4:$A$27,20,Scenario_Results!$B$4:$B$27,TEA_Hydraulics!$E$3,Scenario_Results!$C$4:$C$27,"retrofit")*Global_Assumptions!$B$41+SUMIFS(Scenario_Results!$F$4:$F$27,Scenario_Results!$A$4:$A$27,20,Scenario_Results!$B$4:$B$27,TEA_Hydraulics!$E$3,Scenario_Results!$C$4:$C$27,"retrofit")*Global_Assumptions!$B$50)) | D28: =-B28+C28*$B$3 | E28: =Lifecycle_50yr!$B$15
A29: 20% far new-build | B29: =(SUMIFS(Scenario_Results!$F$4:$F$27,Scenario_Results!$A$4:$A$27,20,Scenario_Results!$B$4:$B$27,TEA_Hydraulics!$E$3,Scenario_Results!$C$4:$C$27,"new")+SUMIFS(Scenario_Results!$G$4:$G$27,Scenario_Results!$A$4:$A$27,20,Scenario_Results!$B$4:$B$27,TEA_Hydraulics!$E$3,Scenario_Results!$C$4:$C$27,"new")+SUMIFS(Scenario_Results!$H$4:$H$27,Scenario_Results!$A$4:$A$27,20,Scenario_Results!$B$4:$B$27,TEA_Hydraulics!$E$3,Scenario_Results!$C$4:$C$27,"new")) | C29: =(INDEX(Blend_Properties!$F$6:$F$13,MATCH(20,Blend_Properties!$A$6:$A$13,0))*Global_Assumptions!$B$66*Lifecycle_50yr!$B$15)+((INDEX(Blend_Properties!$G$6:$G$13,MATCH(20,Blend_Properties!$A$6:$A$13,0))*Global_Assumptions!$B$20+INDEX(Blend_Properties!$F$6:$F$13,MATCH(20,Blend_Properties!$A$6:$A$13,0))*Global_Assumptions!$B$68)*Lifecycle_50yr!$B$15)-(Lifecycle_50yr!$B$18+Lifecycle_50yr!$B$19+(Blend_Properties!$B$3*(1-INDEX(Blend_Properties!$B$6:$B$13,MATCH(20,Blend_Properties!$A$6:$A$13,0)))*Global_Assumptions!$B$16/(1+Global_Assumptions!$B$64*(20/100))*Lifecycle_50yr!$B$15)+(INDEX(Blend_Properties!$F$6:$F$13,MATCH(20,Blend_Properties!$A$6:$A$13,0))*Global_Assumptions!$B$13/(1+Global_Assumptions!$B$64*(20/100))*Lifecycle_50yr!$B$15)+(INDEX(Blend_Properties!$F$6:$F$13,MATCH(20,Blend_Properties!$A$6:$A$13,0))/365*Global_Assumptions!$B$49*Global_Assumptions!$B$48*Global_Assumptions!$B$65*Lifecycle_50yr!$B$15)+((INDEX(Blend_Properties!$F$6:$F$13,MATCH(20,Blend_Properties!$A$6:$A$13,0))*Global_Assumptions!$B$38*Global_Assumptions!$B$19+0.15*INDEX(Blend_Properties!$F$6:$F$13,MATCH(20,Blend_Properties!$A$6:$A$13,0)))*Lifecycle_50yr!$B$15+SUMIFS(Scenario_Results!$G$4:$G$27,Scenario_Results!$A$4:$A$27,20,Scenario_Results!$B$4:$B$27,TEA_Hydraulics!$E$3,Scenario_Results!$C$4:$C$27,"new")*Global_Assumptions!$B$41+SUMIFS(Scenario_Results!$F$4:$F$27,Scenario_Results!$A$4:$A$27,20,Scenario_Results!$B$4:$B$27,TEA_Hydraulics!$E$3,Scenario_Results!$C$4:$C$27,"new")*Global_Assumptions!$B$50)) | D29: =-B29+C29*$B$3 | E29: =Lifecycle_50yr!$B$15
A31: D. NPV vs injection point (20% blend, retrofit)
A32: Scenario | B32: CAPEX ($) | C32: Annual net ($/yr) | D32: NPV 50yr ($) | E32: Avail.
A33: 20% near retrofit | B33: =(SUMIFS(Scenario_Results!$F$4:$F$27,Scenario_Results!$A$4:$A$27,20,Scenario_Results!$B$4:$B$27,TEA_Hydraulics!$B$3,Scenario_Results!$C$4:$C$27,"retrofit")+SUMIFS(Scenario_Results!$G$4:$G$27,Scenario_Results!$A$4:$A$27,20,Scenario_Results!$B$4:$B$27,TEA_Hydraulics!$B$3,Scenario_Results!$C$4:$C$27,"retrofit")+SUMIFS(Scenario_Results!$H$4:$H$27,Scenario_Results!$A$4:$A$27,20,Scenario_Results!$B$4:$B$27,TEA_Hydraulics!$B$3,Scenario_Results!$C$4:$C$27,"retrofit")) | C33: =(INDEX(Blend_Properties!$F$6:$F$13,MATCH(20,Blend_Properties!$A$6:$A$13,0))*Global_Assumptions!$B$66*Lifecycle_50yr!$B$15)+((INDEX(Blend_Properties!$G$6:$G$13,MATCH(20,Blend_Properties!$A$6:$A$13,0))*Global_Assumptions!$B$20+INDEX(Blend_Properties!$F$6:$F$13,MATCH(20,Blend_Properties!$A$6:$A$13,0))*Global_Assumptions!$B$68)*Lifecycle_50yr!$B$15)-(Lifecycle_50yr!$B$18+Lifecycle_50yr!$B$19+(Blend_Properties!$B$3*(1-INDEX(Blend_Properties!$B$6:$B$13,MATCH(20,Blend_Properties!$A$6:$A$13,0)))*Global_Assumptions!$B$16/(1+Global_Assumptions!$B$64*(20/100))*Lifecycle_50yr!$B$15)+(INDEX(Blend_Properties!$F$6:$F$13,MATCH(20,Blend_Properties!$A$6:$A$13,0))*Global_Assumptions!$B$13/(1+Global_Assumptions!$B$64*(20/100))*Lifecycle_50yr!$B$15)+(INDEX(Blend_Properties!$F$6:$F$13,MATCH(20,Blend_Properties!$A$6:$A$13,0))/365*Global_Assumptions!$B$49*Global_Assumptions!$B$48*Global_Assumptions!$B$65*Lifecycle_50yr!$B$15)+((INDEX(Blend_Properties!$F$6:$F$13,MATCH(20,Blend_Properties!$A$6:$A$13,0))*Global_Assumptions!$B$38*Global_Assumptions!$B$19+0.15*INDEX(Blend_Properties!$F$6:$F$13,MATCH(20,Blend_Properties!$A$6:$A$13,0)))*Lifecycle_50yr!$B$15+SUMIFS(Scenario_Results!$G$4:$G$27,Scenario_Results!$A$4:$A$27,20,Scenario_Results!$B$4:$B$27,TEA_Hydraulics!$B$3,Scenario_Results!$C$4:$C$27,"retrofit")*Global_Assumptions!$B$41+SUMIFS(Scenario_Results!$F$4:$F$27,Scenario_Results!$A$4:$A$27,20,Scenario_Results!$B$4:$B$27,TEA_Hydraulics!$B$3,Scenario_Results!$C$4:$C$27,"retrofit")*Global_Assumptions!$B$50)) | D33: =-B33+C33*$B$3 | E33: =Lifecycle_50yr!$B$15
A34: 20% far retrofit | B34: =(SUMIFS(Scenario_Results!$F$4:$F$27,Scenario_Results!$A$4:$A$27,20,Scenario_Results!$B$4:$B$27,TEA_Hydraulics!$E$3,Scenario_Results!$C$4:$C$27,"retrofit")+SUMIFS(Scenario_Results!$G$4:$G$27,Scenario_Results!$A$4:$A$27,20,Scenario_Results!$B$4:$B$27,TEA_Hydraulics!$E$3,Scenario_Results!$C$4:$C$27,"retrofit")+SUMIFS(Scenario_Results!$H$4:$H$27,Scenario_Results!$A$4:$A$27,20,Scenario_Results!$B$4:$B$27,TEA_Hydraulics!$E$3,Scenario_Results!$C$4:$C$27,"retrofit")) | C34: =(INDEX(Blend_Properties!$F$6:$F$13,MATCH(20,Blend_Properties!$A$6:$A$13,0))*Global_Assumptions!$B$66*Lifecycle_50yr!$B$15)+((INDEX(Blend_Properties!$G$6:$G$13,MATCH(20,Blend_Properties!$A$6:$A$13,0))*Global_Assumptions!$B$20+INDEX(Blend_Properties!$F$6:$F$13,MATCH(20,Blend_Properties!$A$6:$A$13,0))*Global_Assumptions!$B$68)*Lifecycle_50yr!$B$15)-(Lifecycle_50yr!$B$18+Lifecycle_50yr!$B$19+(Blend_Properties!$B$3*(1-INDEX(Blend_Properties!$B$6:$B$13,MATCH(20,Blend_Properties!$A$6:$A$13,0)))*Global_Assumptions!$B$16/(1+Global_Assumptions!$B$64*(20/100))*Lifecycle_50yr!$B$15)+(INDEX(Blend_Properties!$F$6:$F$13,MATCH(20,Blend_Properties!$A$6:$A$13,0))*Global_Assumptions!$B$13/(1+Global_Assumptions!$B$64*(20/100))*Lifecycle_50yr!$B$15)+(INDEX(Blend_Properties!$F$6:$F$13,MATCH(20,Blend_Properties!$A$6:$A$13,0))/365*Global_Assumptions!$B$49*Global_Assumptions!$B$48*Global_Assumptions!$B$65*Lifecycle_50yr!$B$15)+((INDEX(Blend_Properties!$F$6:$F$13,MATCH(20,Blend_Properties!$A$6:$A$13,0))*Global_Assumptions!$B$38*Global_Assumptions!$B$19+0.15*INDEX(Blend_Properties!$F$6:$F$13,MATCH(20,Blend_Properties!$A$6:$A$13,0)))*Lifecycle_50yr!$B$15+SUMIFS(Scenario_Results!$G$4:$G$27,Scenario_Results!$A$4:$A$27,20,Scenario_Results!$B$4:$B$27,TEA_Hydraulics!$E$3,Scenario_Results!$C$4:$C$27,"retrofit")*Global_Assumptions!$B$41+SUMIFS(Scenario_Results!$F$4:$F$27,Scenario_Results!$A$4:$A$27,20,Scenario_Results!$B$4:$B$27,TEA_Hydraulics!$E$3,Scenario_Results!$C$4:$C$27,"retrofit")*Global_Assumptions!$B$50)) | D34: =-B34+C34*$B$3 | E34: =Lifecycle_50yr!$B$15

Sheet Use_Case_Summary
A1: COMPILED TEA SUMMARY — UCI Microturbine
A2: Cost breakdown, key drivers, tradeoffs and feasibility thresholds (20% blend, near retrofit).
A4: System type | B4: End-use delivery (low demand)
A5: End use | B5: Capstone C200 microturbine (~200 kW)
A6: Operating/native pressure | B6: 44 psig
A7: H2 demand @20% blend (kg/yr) | B7: =Scenario_Results!D13
A8: Delivered LCOH near @20% ($/kg) | B8: =Scenario_Results!K13
A9: Delivered LCOH far @20% ($/kg) | B9: =Scenario_Results!K14
A10: Annualized CAPEX near ($/yr) | B10: =Scenario_Results!I13
A11: Annual OPEX near ($/yr) | B11: =Scenario_Results!J13
A12: $/tCO2e avoided @20% | B12: =Scenario_Results!M13
A13: Levelized carbon-capture ($/tCO2) | B13: =Scenario_Results!N13
A15: Key economic drivers
A16: • H2 commodity price (dominant on LCOH)
A17: • Injection distance (near vs 100-mi compressors)
A18: • Blend level (raises cost, lowers delivered energy)
A19: • Utilization / demand (inverse on LCOH)
A20: • Delivery pressure (compression cost)
A21: • IRA 45V & LCFS credits (lower net cost)
A23: Feasibility thresholds
A24: Lowest cost: inject near end use, moderate blend (≤20%), lowest workable pressure, capture credits.

Sheet Validation_Tests
A1: MINIMUM VALIDATION TESTS (auto-checked; recalculates on open)
A3: # | B3: Test | C3: Result | D3: Basis / note
A4: 1 | B4: Zero-blend | C4: =IF(AND(Blend_Properties!$F$6=0,Scenario_Results!$G$4=0,Scenario_Results!$L$4=0),"PASS","FAIL") | D4: At 0% H2: demand, H2 CAPEX and CCS cost all zero.
A5: 2 | B5: Baseline (incremental NPV=0) | C5: =IF(ABS(NPV_Comparison!$F$7)<1,"PASS","FAIL") | D5: Incremental NPV at 0% blend is zero by construction.
A6: 3 | B6: Units (LHV consistent) | C6: =IF(ABS(Global_Assumptions!$B$25-Global_Assumptions!$B$24*0.0036)<0.000001,"PASS","FAIL") | D6: H2 GJ/kg equals LHV_kWh x 0.0036.
A7: 4 | B7: Units (no $/kg + $/MWh sum) | C7: =IF(ABS(TEA_Network!$B$8-(TEA_Network!$B$4+TEA_Network!$B$5+TEA_Network!$B$6))<0.000001,"PASS","FAIL") | D7: Network total excludes the $/MWh integration term.
A8: 5 | B8: Policy: 45V capped at 10 yr | C8: =IF(Global_Assumptions!$B$86=10,"PASS","FAIL") | D8: 45V duration input = 10 years; cashflow gates 45V to years 1..10.
A9: 6 | B9: Credit: LCFS=0 in base case | C9: =IF(Global_Assumptions!$B$20=0,"PASS","FAIL") | D9: LCFS is zero unless eligibility toggle = 1.
A10: 7 | B10: Hydraulic: outlet pressure OK | C10: ="PRELIMINARY" | D10: Not modelled — N_comp is a screening proxy; compressible hydraulics is future work.
A11: 8 | B11: Availability consistency | C11: =IF(ABS(Global_Assumptions!$B$11-Lifecycle_50yr!$B$15)<0.000001,"PASS","FAIL") | D11: LCOH and cashflow use the same derived 50-yr mean availability.
A12: 9 | B12: Reconciliation (dashboard/report) | C12: ="MANUAL" | D12: Reconcile to a single engine; SoCalGas workbook not provided in this set.
A13: 10 | B13: Manual benchmark (0/20/100%) | C13: ="MANUAL" | D13: Independently reproduce the 0%, 20% and 100% cases before quoting results.
B15: PASS/FAIL cells recalculate when the file is opened in Excel/LibreOffice.

Sheet Corrections_Log
A1: CORRECTIONS APPLIED (technical review response)
A2: PRELIMINARY / SCREENING ONLY — NON-DECISION-GRADE. These corrections fix boundary, unit, policy and consistency errors so the base case is defensible; they do not turn the suite into an investment-grade model.
A4: Corrected in this revision
A5: 1. Units (LHV) | B5: H2 energy content now LHV-consistent (=33.3 kWh/kg x 0.0036 = 0.11988 GJ/kg). The old 0.113745 was ~5.4% low and overstated H2 mass demand, cost, storage, compression and credits.
A6: 2. IRA 45V | B6: Removed from the base case. Behind an eligibility toggle; earned by the qualified H2 producer, capped at 10 years in the cashflow (was applied ~50 yrs to the end user).
A7: 3. LCFS | B7: Removed from the base case. Behind an eligibility toggle; eligible price repriced to CARB-recent ~$66/tCO2e (was $150). Stationary CHP/kiln/transport eligibility must be documented before use.
A8: 4. Offtake revenue | B8: The $4/kg H2 'production revenue' is OFF in the base case for end uses (a consumer cannot pay for H2 and also book production revenue). Use incremental NPV / avoided-cost framing.
A9: 5. CCS | B9: Now an explicit on/off option (default OFF). Previously CCS cost was charged in EVERY scenario, including 0% H2, inflating LCOH.
A10: 6. Efficiency sign | B10: Combustion efficiency rises slightly with H2 everywhere (Thermoflex); the Cashflow sheet previously used the opposite sign (a derate) vs the Fuel_Cost sheet.
A11: 7. Availability | B11: LCOH now uses the SAME derived 50-yr mean availability as the cashflow (was a fixed 0.97 in LCOH vs ~0.955 derived in the cashflow).
A12: 8. LCOH at 0% | B12: Shown as N/A (no hydrogen exists at 0% blend); removes the -$1.35/kg artefact at 0%.
A13: 9. Network units | B13: TEA_Network total no longer adds $/kg layers to a $/MWh integration term; the stale cached total is refreshed on recalculation.
A14: 10. Incremental NPV | B14: NPV_Comparison now reports NPV incremental to the 0% fossil baseline; the 0% incremental NPV is zero by construction. Absolute 'project' NPV is retained but flagged non-decision-grade.
A16: Still preliminary / not rebuilt
A17: Hydraulics / compressors | B17: N_comp = MAX(1, distance/spacing x flow-factor) is a screening PROXY, not compressible pipeline hydraulics. It does not verify delivery pressure or compute compressor duty from pressure ratio. Do not treat compressor counts or the 3.1 kWh/kg adder as design values.
A18: Reliability PoF | B18: Component PoF are cumulative 'at least one functional failure' probabilities, NOT catastrophic integrity risk, and must not be read alongside rupture probability as equivalent consequence.
A19: Lifecycle degradation | B19: The lifecycle uses a CONSTANT hazard (exponential), not an age-dependent Weibull/renewal model, despite 'PoF rises with age' language. Residual-life claims are indicative only.
A20: Pipe integrity | B20: The FCGR step multipliers are a screening failure-rate multiplier model, NOT probabilistic fracture mechanics. 'Integrity saturates at 20%' is an artefact of the imposed step function, not a physical result.
A21: CAPEX scaling | B21: Pipeline $/mile, the $2M skid and compressor costs are not size/diameter/pressure/location-specific. Small low-utilisation loads (e.g. Fine Arts) show LCOH dominated by fixed-cost dilution, not technology cost.
A22: Equipment limits | B22: The 6.89-bar H2 partial-pressure rule is an API-617 centrifugal-compressor concern, not a universal component acceptance criterion. Replacement CAPEX should follow component-specific qualification.
A23: Prices | B23: H2 $2/kg is optimistic for clean delivered H2 (DOE ~$5-7/kg plant-gate); NG $4.74/GJ and electricity $0.235/kWh should be validated against actual bills/tariffs. Prices are screening placeholders.
A24: Reconciliation | B24: A separate SoCalGas workbook referenced by the review was not provided; only 4 workbooks + the dashboard are in this set. Report/dashboard/workbook reconciliation to a single engine remains outstanding.
